{"meta":{"name":"Music","id":"Marvel41","type":"channel","posterShape":"landscape","videos":[{"id":"Marvelstream_41_0","title":"UK| 4Music"},{"id":"Marvelstream_41_1","title":"UK| Box Hits"},{"id":"Marvelstream_41_2","title":"UK| Brit Asia TV"},{"id":"Marvelstream_41_3","title":"UK| Chart Show Hits"},{"id":"Marvelstream_41_4","title":"UK| Chart Show TV"},{"id":"Marvelstream_41_5","title":"UK| Clubland TV"},{"id":"Marvelstream_41_6","title":"UK| Kerrang!"},{"id":"Marvelstream_41_7","title":"UK| Kiss"},{"id":"Marvelstream_41_8","title":"UK| Magic UK"},{"id":"Marvelstream_41_9","title":"UK| MTV +1"},{"id":"Marvelstream_41_10","title":"UK| MTV Base"},{"id":"Marvelstream_41_11","title":"UK| MTV Classic"},{"id":"Marvelstream_41_12","title":"UK| Spot Light"},{"id":"Marvelstream_41_13","title":"UK| MTV HD"},{"id":"Marvelstream_41_14","title":"UK| MTV SD"},{"id":"Marvelstream_41_15","title":"UK| MTV Hits"},{"id":"Marvelstream_41_16","title":"UK| MTV Live"},{"id":"Marvelstream_41_17","title":"UK| MTV Music"},{"id":"Marvelstream_41_18","title":"UK| MTV Music +1"},{"id":"Marvelstream_41_19","title":"UK| Now  90s"},{"id":"Marvelstream_41_20","title":"UK| Now 80s"},{"id":"Marvelstream_41_21","title":"UK| The Box"},{"id":"Marvelstream_41_22","title":"UK| The Vault"},{"id":"Marvelstream_41_23","title":"UK| VH1"},{"id":"Marvelstream_41_24","title":"UK| Now 70s"}]}}