{"meta":{"name":"BT Sport Extra","id":"Marvel45","type":"channel","posterShape":"landscape","videos":[{"id":"Marvelstream_45_0","title":"UK| BT Sport Extra 1"},{"id":"Marvelstream_45_1","title":"UK| BT Sport Extra 2"},{"id":"Marvelstream_45_2","title":"UK| BT Sport Extra 3"},{"id":"Marvelstream_45_3","title":"UK| BT Sport Extra 4"},{"id":"Marvelstream_45_4","title":"UK| BT Sport Extra 5"},{"id":"Marvelstream_45_5","title":"UK| BT Sport Extra 6"},{"id":"Marvelstream_45_6","title":"UK| BT Sport Extra 7"}]}}