{"meta":{"name":"USA Backup","id":"marveldc28","type":"channel","posterShape":"landscape","videos":[{"id":"marveldcstream_28_0","title":"WXYZ|ABC Detroit|Michigan (US/CA | Regional)"},{"id":"marveldcstream_28_1","title":"WSB|ABC Atlanta|Georgia (US/CA | Regional)"},{"id":"marveldcstream_28_2","title":"WPLG|ABC Miami|Florida (US/CA | Regional)"},{"id":"marveldcstream_28_3","title":"WFTV|ABC Orlando|Florida (US/CA | Regional)"},{"id":"marveldcstream_28_4","title":"WFAA|ABC Dallas|Fort Worth|Texas (US/CA | Regional)"},{"id":"marveldcstream_28_5","title":"WABC|ABC New York (US/CA | Regional)"},{"id":"marveldcstream_28_6","title":"KTRK|ABC Houston|Texas (US/CA | Regional)"},{"id":"marveldcstream_28_7","title":"KNXV|ABC Phoenix|Arizona (US/CA | Regional)"},{"id":"marveldcstream_28_8","title":"KMGH|ABC Denver|Colorado (US/CA | Regional)"},{"id":"marveldcstream_28_9","title":"KABC|ABC Los Angeles|California (US/CA | Regional)"},{"id":"marveldcstream_28_10","title":"====== ABC Locals ======"},{"id":"marveldcstream_28_11","title":"WXTV|Univision Paterson|New Jersey/New York|New York (US/CA | Regional)"},{"id":"marveldcstream_28_12","title":"WUVP|Univision Vineland|New Jersey (US/CA | Regional)"},{"id":"marveldcstream_28_13","title":"WUVG|Univision Athens|Georgia (US/CA | Regional)"},{"id":"marveldcstream_28_14","title":"WQHS|Univision Cleveland|Ohio (US/CA | Regional)"},{"id":"marveldcstream_28_15","title":"WLTV|Univision Miami|Florida (US/CA | Regional)"},{"id":"marveldcstream_28_16","title":"WGBO|Univision Joliet|Illinois (US/CA | Regional)"},{"id":"marveldcstream_28_17","title":"KXLN|Univision Rosenberg|Texas (US/CA | Regional)"},{"id":"marveldcstream_28_18","title":"KUVN|Univision Garland|Texas (US/CA | Regional)"},{"id":"marveldcstream_28_19","title":"KTVW|Univision Phoenix|Arizona (US/CA | Regional)"},{"id":"marveldcstream_28_20","title":"KMEX|Univision Los Angeles|California (US/CA | Regional)"},{"id":"marveldcstream_28_21","title":"KFTR|Univision Ontario|California (US/CA | Regional)"},{"id":"marveldcstream_28_22","title":"KFSF|Univision Vallejo|California (US/CA | Regional)"},{"id":"marveldcstream_28_23","title":"KFPH|Univision Flagstaff|Arizona (US/CA | Regional)"},{"id":"marveldcstream_28_24","title":"KDTV|Univision San Francisco|California (US/CA | Regional)"},{"id":"marveldcstream_28_25","title":"KAKW|Univision Killeen|Texas (US/CA | Regional)"},{"id":"marveldcstream_28_26","title":"====== Univision Locals ======"},{"id":"marveldcstream_28_27","title":"WXFT|Unimas Aurora|Illinois (US/CA | Regional)"},{"id":"marveldcstream_28_28","title":"WFUT|Unimas Newark|New Jersey (US/CA | Regional)"},{"id":"marveldcstream_28_29","title":"WFPA|Unimas Philadelphia|Pennsylvania (US/CA | Regional)"},{"id":"marveldcstream_28_30","title":"WAMI|Unimas Hollywood|Florida (US/CA | Regional)"},{"id":"marveldcstream_28_31","title":"KTFO|Unimas Austin|Texas (US/CA | Regional)"},{"id":"marveldcstream_28_32","title":"KSTR|Unimas Irving|Texas (US/CA | Regional)"},{"id":"marveldcstream_28_33","title":"====== Unimas Locals ======"},{"id":"marveldcstream_28_34","title":"WZDC|Telemundo Washington|D.C. (US/CA | Regional)"},{"id":"marveldcstream_28_35","title":"WTMO|Telemundo Orlando|Florida (US/CA | Regional)"},{"id":"marveldcstream_28_36","title":"WSNS|Telemundo Chicago|Illinois (US/CA | Regional)"},{"id":"marveldcstream_28_37","title":"WSCV|Telemundo Fort Lauderdale|Florida (US/CA | Regional)"},{"id":"marveldcstream_28_38","title":"WRMD|Telemundo Tampa|Florida (US/CA | Regional)"},{"id":"marveldcstream_28_39","title":"WRDM|Telemundo Hartford|Connecticut (US/CA | Regional)"},{"id":"marveldcstream_28_40","title":"WNJU|Telemundo Linden|New Jersey (US/CA | Regional)"},{"id":"marveldcstream_28_41","title":"WNEU|Telemundo Merrimack|New Hampshire (US/CA | Regional)"},{"id":"marveldcstream_28_42","title":"WKTB|Telemundo Atlanta (US/CA | Regional)"},{"id":"marveldcstream_28_43","title":"KXTX|Telemundo Dallas|Texas (US/CA | Regional)"},{"id":"marveldcstream_28_44","title":"KVEA|Telemundo Corona|California (US/CA | Regional)"},{"id":"marveldcstream_28_45","title":"KTUZ|Telemundo Shawnee|Oklahoma (US/CA | Regional)"},{"id":"marveldcstream_28_46","title":"KTMW|Telemundo Salt Lake City|Utah (US/CA | Regional)"},{"id":"marveldcstream_28_47","title":"KTAZ|Telemundo Phoenix|Arizona (US/CA | Regional)"},{"id":"marveldcstream_28_48","title":"KSTS|Telemundo San Jose|California (US/CA | Regional)"},{"id":"marveldcstream_28_49","title":"KQRE|Telemundo Bend|Oregon (US/CA | Regional)"},{"id":"marveldcstream_28_50","title":"KGLA|Telemundo Hammond|Louisiana (US/CA | Regional)"},{"id":"marveldcstream_28_51","title":"KDEN|Telemundo Longmont|Colorado (US/CA | Regional)"},{"id":"marveldcstream_28_52","title":"KCSO|Telemundo Sacramento|California (US/CA | Regional)"},{"id":"marveldcstream_28_53","title":"KBLR|Telemundo Paradise|Nevada (US/CA | Regional)"},{"id":"marveldcstream_28_54","title":"====== Telemundo Locals ======"},{"id":"marveldcstream_28_55","title":"WXIA|NBC Atlanta|Georgia (US/CA | Regional)"},{"id":"marveldcstream_28_56","title":"WTVJ|NBC Miami|Florida (US/CA | Regional)"},{"id":"marveldcstream_28_57","title":"WSFA|NBC Montgomery|Alabama (US/CA | Regional)"},{"id":"marveldcstream_28_58","title":"WRC|NBC Washington|D.C. (US/CA | Regional)"},{"id":"marveldcstream_28_59","title":"WPXI|NBC Pittsburgh|Pennsylvania (US/CA | Regional)"},{"id":"marveldcstream_28_60","title":"WOWT|NBC Omaha|Nebraska (US/CA | Regional)"},{"id":"marveldcstream_28_61","title":"WNBC|NBC New York (US/CA | Regional)"},{"id":"marveldcstream_28_62","title":"WMTV|NBC Madison|Wisconsin (US/CA | Regional)"},{"id":"marveldcstream_28_63","title":"WMFP|NBC Foxborough|Massachusetts (US/CA | Regional)"},{"id":"marveldcstream_28_64","title":"WMAQ|NBC Chicago|Illinois (US/CA | Regional)"},{"id":"marveldcstream_28_65","title":"WKYC|NBC Cleveland|Ohio (US/CA | Regional)"},{"id":"marveldcstream_28_66","title":"WJAR|NBC Providence|Rhode Island (US/CA | Regional)"},{"id":"marveldcstream_28_67","title":"WIS|NBC Columbia|South Carolina (US/CA | Regional)"},{"id":"marveldcstream_28_68","title":"WGRZ|NBC Buffalo|New York (US/CA | Regional)"},{"id":"marveldcstream_28_69","title":"WDSU|NBC New Orleans|Louisiana (US/CA | Regional)"},{"id":"marveldcstream_28_70","title":"WCNC|NBC Charlotte|North Carolina (US/CA | Regional)"},{"id":"marveldcstream_28_71","title":"WCMH|NBC Columbus|Ohio (US/CA | Regional)"},{"id":"marveldcstream_28_72","title":"WBRE|NBC Wilkes Barre|Pennsylvania (US/CA | Regional)"},{"id":"marveldcstream_28_73","title":"WBOY|NBC Clarksburg|West Virginia (US/CA | Regional)"},{"id":"marveldcstream_28_74","title":"WBAL|NBC Baltimore|Maryland (US/CA | Regional)"},{"id":"marveldcstream_28_75","title":"KXAS|NBC Fort Worth|Dallas (US/CA | Regional)"},{"id":"marveldcstream_28_76","title":"KXAN|NBC Austin|Texas (US/CA | Regional)"},{"id":"marveldcstream_28_77","title":"KUSA|NBC Denver|Colorado (US/CA | Regional)"},{"id":"marveldcstream_28_78","title":"KSNV|NBC Las Vegas|Nevada (US/CA | Regional)"},{"id":"marveldcstream_28_79","title":"KSL|NBC Salt Lake City|Utah (US/CA | Regional)"},{"id":"marveldcstream_28_80","title":"KPRC|NBC Houston|Texas (US/CA | Regional)"},{"id":"marveldcstream_28_81","title":"KPNX|NBC Mesa|Arizona (US/CA | Regional)"},{"id":"marveldcstream_28_82","title":"KNTV|NBC San Jose|California (US/CA | Regional)"},{"id":"marveldcstream_28_83","title":"KNBC|NBC Los Angeles (US/CA | Regional)"},{"id":"marveldcstream_28_84","title":"KING|NBC Seattle|Washington (US/CA | Regional)"},{"id":"marveldcstream_28_85","title":"KHNL|NBC Honolulu|Hawaii (US/CA | Regional)"},{"id":"marveldcstream_28_86","title":"KDLT|NBC Sioux Falls|South Dakota (US/CA | Regional)"},{"id":"marveldcstream_28_87","title":"KCRA|NBC Sacramento|California (US/CA | Regional)"},{"id":"marveldcstream_28_88","title":"KCHY|NBC Casper|Wyoming (US/CA | Regional)"},{"id":"marveldcstream_28_89","title":"====== NBC Locals ======"},{"id":"marveldcstream_28_90","title":"WVUE|Fox New Orleans|Louisiana (US/CA | Regional)"},{"id":"marveldcstream_28_91","title":"WTTG|Fox Washington|D.C. (US/CA | Regional)"},{"id":"marveldcstream_28_92","title":"WTIC|Fox Hartford|Connecticut (US/CA | Regional)"},{"id":"marveldcstream_28_93","title":"WSVN|Fox Miami|Florida (US/CA | Regional)"},{"id":"marveldcstream_28_94","title":"WPWR|Fox Gary|Indiana (US/CA | Regional)"},{"id":"marveldcstream_28_95","title":"WNYW|Fox New York (US/CA | Regional)"},{"id":"marveldcstream_28_96","title":"WNAC|Fox Providence|Rhode Island (US/CA | Regional)"},{"id":"marveldcstream_28_97","title":"WJZY|Fox Belmont|North Carolina (US/CA | Regional)"},{"id":"marveldcstream_28_98","title":"WJW|Fox Cleveland|Ohio (US/CA | Regional)"},{"id":"marveldcstream_28_99","title":"WITI|Fox Milwaukee|Wisconsin (US/CA | Regional)"},{"id":"marveldcstream_28_100","title":"WHNS|Fox Greenville|South Carolina (US/CA | Regional)"},{"id":"marveldcstream_28_101","title":"WFXT|Fox Boston|Massachusetts (US/CA | Regional)"},{"id":"marveldcstream_28_102","title":"WFLD|Fox Chicago|Illinois (US/CA | Regional)"},{"id":"marveldcstream_28_103","title":"WAGA|Fox Atlanta|Georgia (US/CA | Regional)"},{"id":"marveldcstream_28_104","title":"KVVU|Fox Henderson|Nevada (US/CA | Regional)"},{"id":"marveldcstream_28_105","title":"KTXL|Fox Sacramento|California (US/CA | Regional)"},{"id":"marveldcstream_28_106","title":"KTVU|Fox Oakland|California (US/CA | Regional)"},{"id":"marveldcstream_28_107","title":"KTVI|Fox St. Louis|Missouri (US/CA | Regional)"},{"id":"marveldcstream_28_108","title":"KTTW|Fox Sioux Falls|South Dakota (US/CA | Regional)"},{"id":"marveldcstream_28_109","title":"KTTV|Fox Los Angeles|California (US/CA | Regional)"},{"id":"marveldcstream_28_110","title":"KTBC|Fox Austin|Texas (US/CA | Regional)"},{"id":"marveldcstream_28_111","title":"KSTU|Fox Salt Lake City|Utah (US/CA | Regional)"},{"id":"marveldcstream_28_112","title":"KSAZ|Fox Phoenix|Arizona (US/CA | Regional)"},{"id":"marveldcstream_28_113","title":"KRIV|Fox Houston|Texas (US/CA | Regional)"},{"id":"marveldcstream_28_114","title":"KICU|Fox San Jose|California (US/CA | Regional)"},{"id":"marveldcstream_28_115","title":"KHON|Fox Honolulu|Hawaii (US/CA | Regional)"},{"id":"marveldcstream_28_116","title":"KDVR|Fox Denver|Colorado (US/CA | Regional)"},{"id":"marveldcstream_28_117","title":"KDFW|Fox Dallas|Texas (US/CA | Regional)"},{"id":"marveldcstream_28_118","title":"KCPQ|Fox Tacoma|Washington (US/CA | Regional)"},{"id":"marveldcstream_28_119","title":"====== FOX Locals ======"},{"id":"marveldcstream_28_120","title":"WYOU|CBS Scranton|Pennsylvania (US/CA | Regional)"},{"id":"marveldcstream_28_121","title":"WWL|CBS New Orleans|Louisiana (US/CA | Regional)"},{"id":"marveldcstream_28_122","title":"WUSA|CBS Washington|D.C. (US/CA | Regional)"},{"id":"marveldcstream_28_123","title":"WUPA|CBS Atlanta|Georgia (US/CA | Regional)"},{"id":"marveldcstream_28_124","title":"WSPA|CBS Spartanburg|South Carolina (US/CA | Regional)"},{"id":"marveldcstream_28_125","title":"WPRI|CBS Providence|Rhode Island (US/CA | Regional)"},{"id":"marveldcstream_28_126","title":"WOIO|CBS Shaker Heights/Cleveland|Ohio (US/CA | Regional)"},{"id":"marveldcstream_28_127","title":"WLTX|CBS Columbia|South Carolina (US/CA | Regional)"},{"id":"marveldcstream_28_128","title":"WLNY|CBS Riverhead|New York (US/CA | Regional)"},{"id":"marveldcstream_28_129","title":"WJZ|CBS|Baltimore (US/CA | Regional)"},{"id":"marveldcstream_28_130","title":"WIVB|CBS Buffalo|New York (US/CA | Regional)"},{"id":"marveldcstream_28_131","title":"WISC|CBS Madison|Wisconsin (US/CA | Regional)"},{"id":"marveldcstream_28_132","title":"WGCL|CBS Atlanta|Georgia (US/CA | Regional)"},{"id":"marveldcstream_28_133","title":"WFOR|CBS Miami|Fort Lauderdale (US/CA | Regional)"},{"id":"marveldcstream_28_134","title":"WCBS|CBS New York (US/CA | Regional)"},{"id":"marveldcstream_28_135","title":"WBZ|CBS Boston (US/CA | Regional)"},{"id":"marveldcstream_28_136","title":"WBTV|CBS Charlotte|North Carolina (US/CA | Regional)"},{"id":"marveldcstream_28_137","title":"WBNS|CBS Columbus|Ohio (US/CA | Regional)"},{"id":"marveldcstream_28_138","title":"WBFS|CBS Miami|Florida (US/CA | Regional)"},{"id":"marveldcstream_28_139","title":"WBBM|CBS Chicago (US/CA | Regional)"},{"id":"marveldcstream_28_140","title":"WAKA|CBS Selma|Alabama (US/CA | Regional)"},{"id":"marveldcstream_28_141","title":"KWTV|CBS Oklahoma City|Oklahoma (US/CA | Regional)"},{"id":"marveldcstream_28_142","title":"KUTV|CBS Salt Lake City|Utah (US/CA | Regional)"},{"id":"marveldcstream_28_143","title":"KTXA|CBS Fort Worth|Texas (US/CA | Regional)"},{"id":"marveldcstream_28_144","title":"KTVT|CBS Fort Worth|Dallas (US/CA | Regional)"},{"id":"marveldcstream_28_145","title":"KSTW|CBS Tacoma–Seattle|Washington (US/CA | Regional)"},{"id":"marveldcstream_28_146","title":"KPIX|CBS San Francisco|Oakland|San Jose (US/CA | Regional)"},{"id":"marveldcstream_28_147","title":"KPHO|CBS Phoenix|Arizona (US/CA | Regional)"},{"id":"marveldcstream_28_148","title":"KMTV|CBS Omaha|Nebraska (US/CA | Regional)"},{"id":"marveldcstream_28_149","title":"KMOV|CBS St. Louis|Missouri (US/CA | Regional)"},{"id":"marveldcstream_28_150","title":"KLAS|CBS Las Vegas|Nevada (US/CA | Regional)"},{"id":"marveldcstream_28_151","title":"KIRO|CBS Seattle|Washington (US/CA | Regional)"},{"id":"marveldcstream_28_152","title":"KHOU|CBS Houston|Texas (US/CA | Regional)"},{"id":"marveldcstream_28_153","title":"KGMB|CBS Honolulu|Hawaii (US/CA | Regional)"},{"id":"marveldcstream_28_154","title":"KELO |CBS Sioux Falls|South Dakota (US/CA | Regional)"},{"id":"marveldcstream_28_155","title":"KDKA|CBS Pittsburgh (US/CA | Regional)"},{"id":"marveldcstream_28_156","title":"KCNC|CBS Denver (US/CA | Regional)"},{"id":"marveldcstream_28_157","title":"KCCI|CBS Des Moines|Iowa (US/CA | Regional)"},{"id":"marveldcstream_28_158","title":"KCBS|CBS Los Angeles (US/CA | Regional)"},{"id":"marveldcstream_28_159","title":"KCAL|CBS Los Angeles|California (US/CA | Regional)"},{"id":"marveldcstream_28_160","title":"KBCW|CBS San Francisco|California (US/CA | Regional)"},{"id":"marveldcstream_28_161","title":"====== CBS Locals ======"},{"id":"marveldcstream_28_162","title":"ESPN3 HD* (US/CA | Main)"},{"id":"marveldcstream_28_163","title":"NewsMax TV HD* (US/CA | Main)"},{"id":"marveldcstream_28_164","title":"Newsmax Channel HD* (US/CA | Main)"},{"id":"marveldcstream_28_165","title":"NE Cable News HD* (US/CA | Main)"},{"id":"marveldcstream_28_166","title":"MSNBC HD* (US/CA | Main)"},{"id":"marveldcstream_28_167","title":"Fox News HD* (US/CA | Main)"},{"id":"marveldcstream_28_168","title":"Fox Business HD* (US/CA | Main)"},{"id":"marveldcstream_28_169","title":"CP24 HD* (US/CA | Main)"},{"id":"marveldcstream_28_170","title":"CNN HD* (US/CA | Main)"},{"id":"marveldcstream_28_171","title":"CNBC World HD* (US/CA | Main)"},{"id":"marveldcstream_28_172","title":"CNBC HD* (US/CA | Main)"},{"id":"marveldcstream_28_173","title":"Cheddar News HD* (US/CA | Main)"},{"id":"marveldcstream_28_174","title":"Cheddar Business HD* (US/CA | Main)"},{"id":"marveldcstream_28_175","title":"CBS News HD* (US/CA | Main)"},{"id":"marveldcstream_28_176","title":"Bloomberg HD* (US/CA | Main)"},{"id":"marveldcstream_28_177","title":"BBC World News HD* (US/CA | Main)"},{"id":"marveldcstream_28_178","title":"ABC News HD* (US/CA | Main)"},{"id":"marveldcstream_28_179","title":"=== USA News ==="},{"id":"marveldcstream_28_180","title":"MC | Wonderama (US/CA | Main)"},{"id":"marveldcstream_28_181","title":"MC | Youth Hits (US/CA | Main)"},{"id":"marveldcstream_28_182","title":"MC | Adult Alternative (US/CA | Main)"},{"id":"marveldcstream_28_183","title":"MC | Ladies of R&B (US/CA | Main) "},{"id":"marveldcstream_28_184","title":"MC | R&B 2K (US/CA | Main)"},{"id":"marveldcstream_28_185","title":"MC | Soft Rock (US/CA | Main)"},{"id":"marveldcstream_28_186","title":"MC | 80's Music Video "},{"id":"marveldcstream_28_187","title":"MC | Radio Disney (US/CA | Main)"},{"id":"marveldcstream_28_188","title":"MC | Music Choice Play (US/CA | Main)"},{"id":"marveldcstream_28_189","title":"MC | Learn & Play (US/CA | Main)"},{"id":"marveldcstream_28_190","title":"MC | Y2K (US/CA | Main)"},{"id":"marveldcstream_28_191","title":"MC | Country Hits (US/CA | Main)"},{"id":"marveldcstream_28_192","title":"MC | Pop Latino (US/CA | Main)"},{"id":"marveldcstream_28_193","title":"MC | Musica Urbana (US/CA | Main)"},{"id":"marveldcstream_28_194","title":"MC | Music Choice Max (US/CA | Main)"},{"id":"marveldcstream_28_195","title":"MC | Mexicana (US/CA | Main)"},{"id":"marveldcstream_28_196","title":"MC | Kidz Only! (US/CA | Main)"},{"id":"marveldcstream_28_197","title":"MC | Kidz Bop (US/CA | Main)"},{"id":"marveldcstream_28_198","title":"MC | Brits + Hits (US/CA | Main)"},{"id":"marveldcstream_28_199","title":"MC | Alternative (US/CA | Main)"},{"id":"marveldcstream_28_200","title":"MC | Tropicales Music Videos (US/CA | Main)"},{"id":"marveldcstream_28_201","title":"MC | Toddler Tunes Music Videos (US/CA | Main)"},{"id":"marveldcstream_28_202","title":"MC | Todays Country Music Videos (US/CA | Main)"},{"id":"marveldcstream_28_203","title":"MC | Throwback Jamz Music Videos (US/CA | Main)"},{"id":"marveldcstream_28_204","title":"MC | Teen Beats Music Videos (US/CA | Main)"},{"id":"marveldcstream_28_205","title":"MC | Rock Music Videos (US/CA | Main)"},{"id":"marveldcstream_28_206","title":"MC | Rap Music Videos (US/CA | Main)"},{"id":"marveldcstream_28_207","title":"MC | Rap 2K Music Videos (US/CA | Main)"},{"id":"marveldcstream_28_208","title":"MC | R & B Soul Music Videos (US/CA | Main)"},{"id":"marveldcstream_28_209","title":"MC | Pop Hits Music Videos (US/CA | Main)"},{"id":"marveldcstream_28_210","title":"MC | Pop & Country Music Videos (US/CA | Main)"},{"id":"marveldcstream_28_211","title":"MC | Metal Music Videos (US/CA | Main)"},{"id":"marveldcstream_28_212","title":"MC | Indie Music Videos (US/CA | Main)"},{"id":"marveldcstream_28_213","title":"MC | Hit List Music Videos (US/CA | Main)"},{"id":"marveldcstream_28_214","title":"MC | Hip Hop and R & B Music Videos (US/CA | Main)"},{"id":"marveldcstream_28_215","title":"MC | Dance EDM Music Videos (US/CA | Main)"},{"id":"marveldcstream_28_216","title":"MC | 90s Music Video (US/CA | Main)"},{"id":"marveldcstream_28_217","title":"=== USA Music ==="},{"id":"marveldcstream_28_218","title":"YTV HD* (US/CA | Main)"},{"id":"marveldcstream_28_219","title":"Universal Kids HD* (US/CA | Main)"},{"id":"marveldcstream_28_220","title":"Treehouse HD* (US/CA | Main)"},{"id":"marveldcstream_28_221","title":"Teen Nick HD* (US/CA | Main)"},{"id":"marveldcstream_28_222","title":"Pop TV HD* (US/CA | Main)"},{"id":"marveldcstream_28_223","title":"Nicktoons HD* (US/CA | Main)"},{"id":"marveldcstream_28_224","title":"Nickelodeon HD* (US/CA | Main)"},{"id":"marveldcstream_28_225","title":"Nick Music HD* (US/CA | Main)"},{"id":"marveldcstream_28_226","title":"NIck Jr. HD* (US/CA | Main)"},{"id":"marveldcstream_28_227","title":"Disney XD HD* (US/CA | Main)"},{"id":"marveldcstream_28_228","title":"Disney Junior HD* (US/CA | Main)"},{"id":"marveldcstream_28_229","title":"Disney Channel HD* (US/CA | Main)"},{"id":"marveldcstream_28_230","title":"Cartoon Network HD* (US/CA | Main)"},{"id":"marveldcstream_28_231","title":"Boomerang HD* (US/CA | Main)"},{"id":"marveldcstream_28_232","title":"Baby TV HD* (US/CA | Main)"},{"id":"marveldcstream_28_233","title":"=== USA Kids ==="},{"id":"marveldcstream_28_234","title":"Zona Futbol HD* (US/CA | Main)"},{"id":"marveldcstream_28_235","title":"Yes Network HD* (US/CA | Main)"},{"id":"marveldcstream_28_236","title":"WWE Network HD* (US/CA | Main)"},{"id":"marveldcstream_28_237","title":"World Fishing Network HD* (US/CA | Main)"},{"id":"marveldcstream_28_238","title":"UFC 24/7 TV HD* (US/CA | Main)"},{"id":"marveldcstream_28_239","title":"TYC Sports HD* (US/CA | Main)"},{"id":"marveldcstream_28_240","title":"TVG Racing Network HD* (US/CA | Main)"},{"id":"marveldcstream_28_241","title":"TVG Racing Network Alt HD* (US/CA | Main)"},{"id":"marveldcstream_28_242","title":"TSN 5 HD* (US/CA | Main)"},{"id":"marveldcstream_28_243","title":"TSN 4 HD* (US/CA | Main)"},{"id":"marveldcstream_28_244","title":"TSN 3 HD* (US/CA | Main)"},{"id":"marveldcstream_28_245","title":"TSN 2 HD* (US/CA | Main)"},{"id":"marveldcstream_28_246","title":"TSN 1 HD* (US/CA | Main)"},{"id":"marveldcstream_28_247","title":"TNT HD* (US/CA | Main)"},{"id":"marveldcstream_28_248","title":"The Golf Channel HD* (US/CA | Main)"},{"id":"marveldcstream_28_249","title":"Tennis Channel HD* (US/CA | Main)"},{"id":"marveldcstream_28_250","title":"Stadium HD* (US/CA | Main)"},{"id":"marveldcstream_28_251","title":"Stadium 3 HD* (US/CA | Main)"},{"id":"marveldcstream_28_252","title":"Stadium 2 HD* (US/CA | Main)"},{"id":"marveldcstream_28_253","title":"Stadium 1 HD* (US/CA | Main)"},{"id":"marveldcstream_28_254","title":"Sportsman Channel HD* (US/CA | Main)"},{"id":"marveldcstream_28_255","title":"Sec Network HD* (US/CA | Main)"},{"id":"marveldcstream_28_256","title":"PAC 12 Washington HD* (US/CA | Main)"},{"id":"marveldcstream_28_257","title":"PAC 12 Oregon HD* (US/CA | Main)"},{"id":"marveldcstream_28_258","title":"PAC 12 Network HD* (US/CA | Main)"},{"id":"marveldcstream_28_259","title":"PAC 12 Mountain HD* (US/CA | Main)"},{"id":"marveldcstream_28_260","title":"PAC 12 LA HD* (US/CA | Main)"},{"id":"marveldcstream_28_261","title":"PAC 12 Bay Area HD* (US/CA | Main)"},{"id":"marveldcstream_28_262","title":"PAC 12 Arizona HD* (US/CA | Main)"},{"id":"marveldcstream_28_263","title":"Outside HD* (US/CA | Main)"},{"id":"marveldcstream_28_264","title":"Outdoor Channel HD* (US/CA | Main)"},{"id":"marveldcstream_28_265","title":"NHL Network HD* (US/CA | Main)"},{"id":"marveldcstream_28_266","title":"NFL Redzone HD* (US/CA | Main)"},{"id":"marveldcstream_28_267","title":"NFL Network HD* (US/CA | Main)"},{"id":"marveldcstream_28_268","title":"NESN HD* (US/CA | Main)"},{"id":"marveldcstream_28_269","title":"NBCSN HD* (US/CA | Main)"},{"id":"marveldcstream_28_270","title":"NBC Washington HD* (US/CA | Main)"},{"id":"marveldcstream_28_271","title":"NBC SNY HD* (US/CA | Main)"},{"id":"marveldcstream_28_272","title":"NBC Phili HD* (US/CA | Main)"},{"id":"marveldcstream_28_273","title":"NBC Olympic HD* (US/CA | Main)"},{"id":"marveldcstream_28_274","title":"NBC North West HD* (US/CA | Main)"},{"id":"marveldcstream_28_275","title":"NBC Chicago Plus HD* (US/CA | Main)"},{"id":"marveldcstream_28_276","title":"NBC Chicago HD* (US/CA | Main)"},{"id":"marveldcstream_28_277","title":"NBC California Plus HD* (US/CA | Main)"},{"id":"marveldcstream_28_278","title":"NBC California HD* (US/CA | Main)"},{"id":"marveldcstream_28_279","title":"NBC Boston HD* (US/CA | Main)"},{"id":"marveldcstream_28_280","title":"NBC Bay Area HD* (US/CA | Main)"},{"id":"marveldcstream_28_281","title":"NBA TV HD* (US/CA | Main)"},{"id":"marveldcstream_28_282","title":"MSG+ 222 HD* (US/CA | Main)"},{"id":"marveldcstream_28_283","title":"MSG+ 22 HD* (US/CA | Main)"},{"id":"marveldcstream_28_284","title":"MSG HD* (US/CA | Main)"},{"id":"marveldcstream_28_285","title":"MSG 2 HD* (US/CA | Main)"},{"id":"marveldcstream_28_286","title":"MLB StrikeZone HD* (US/CA | Main)"},{"id":"marveldcstream_28_287","title":"MLB Network HD* (US/CA | Main)"},{"id":"marveldcstream_28_288","title":"Mav TV HD* (US/CA | Main)"},{"id":"marveldcstream_28_289","title":"Longhorn Network HD* (US/CA | Main)"},{"id":"marveldcstream_28_290","title":"GolTV (Spanish) HD* (US/CA | Main)"},{"id":"marveldcstream_28_291","title":"Gnix Sports TV HD* (US/CA | Main)"},{"id":"marveldcstream_28_292","title":"GAME+ HD* (US/CA | Main)"},{"id":"marveldcstream_28_293","title":"Fubo Sports Network HD* (US/CA | Main)"},{"id":"marveldcstream_28_294","title":"Fox Sports Wisconsin HD* (US/CA | Main)"},{"id":"marveldcstream_28_295","title":"Fox Sports West HD* (US/CA | Main)"},{"id":"marveldcstream_28_296","title":"Fox Sports Tennessee HD* (US/CA | Main)"},{"id":"marveldcstream_28_297","title":"Fox Sports Sun HD* (US/CA | Main)"},{"id":"marveldcstream_28_298","title":"Fox Sports South West HD* (US/CA | Main)"},{"id":"marveldcstream_28_299","title":"Fox Sports South HD* (US/CA | Main)"},{"id":"marveldcstream_28_300","title":"Fox Sports South East HD* (US/CA | Main)"},{"id":"marveldcstream_28_301","title":"Fox Sports San Diego HD* (US/CA | Main)"},{"id":"marveldcstream_28_302","title":"Fox Sports Prime Ticket HD* (US/CA | Main)"},{"id":"marveldcstream_28_303","title":"Fox Sports Oklahoma HD* (US/CA | Main)"},{"id":"marveldcstream_28_304","title":"Fox Sports Ohio HD* (US/CA | Main)"},{"id":"marveldcstream_28_305","title":"Fox Sports North HD* (US/CA | Main)"},{"id":"marveldcstream_28_306","title":"Fox Sports New Orleans HD* (US/CA | Main)"},{"id":"marveldcstream_28_307","title":"Fox Sports Midwest HD* (US/CA | Main)"},{"id":"marveldcstream_28_308","title":"Fox Sports Indiana HD* (US/CA | Main)"},{"id":"marveldcstream_28_309","title":"Fox Sports Florida HD* (US/CA | Main)"},{"id":"marveldcstream_28_310","title":"Fox Sports Detroit HD* (US/CA | Main)"},{"id":"marveldcstream_28_311","title":"Fox Sports Deportes HD* (US/CA | Main)"},{"id":"marveldcstream_28_312","title":"Fox Sports Carolinas HD* (US/CA | Main)"},{"id":"marveldcstream_28_313","title":"Fox Sports Arizona HD* (US/CA | Main)"},{"id":"marveldcstream_28_314","title":"Fox Sports 2 HD* (US/CA | Main)"},{"id":"marveldcstream_28_315","title":"Fox Sports 1 HD* (US/CA | Main)"},{"id":"marveldcstream_28_316","title":"Fox Soccer Plus HD* (US/CA | Main)"},{"id":"marveldcstream_28_317","title":"Fox College Sports Atlantic HD* (US/CA | Main)"},{"id":"marveldcstream_28_318","title":"FNTSY Sports Network HD* (US/CA | Main)"},{"id":"marveldcstream_28_319","title":"Fight Network HD* (US/CA | Main)"},{"id":"marveldcstream_28_320","title":"ESPNU HD* (US/CA | Main)"},{"id":"marveldcstream_28_321","title":"ESPNews HD* (US/CA | Main)"},{"id":"marveldcstream_28_322","title":"ESPN2 HD* (US/CA | Main)"},{"id":"marveldcstream_28_323","title":"ESPN HD* (US/CA | Main)"},{"id":"marveldcstream_28_324","title":"ESPN Deportes HD* (US/CA | Main)"},{"id":"marveldcstream_28_325","title":"ESPN Bases Loaded HD* (US/CA | Main)"},{"id":"marveldcstream_28_326","title":"Eleven Sports Network HD* (US/CA | Main)"},{"id":"marveldcstream_28_327","title":"CBS Sports Network HD* (US/CA | Main)"},{"id":"marveldcstream_28_328","title":"CBS Sports HQ HD* (US/CA | Main)"},{"id":"marveldcstream_28_329","title":"BTN HD* (US/CA | Main)"},{"id":"marveldcstream_28_330","title":"BTN Alternate HD* (US/CA | Main)"},{"id":"marveldcstream_28_331","title":"beiN Sports La Liga HD* (US/CA | Main)"},{"id":"marveldcstream_28_332","title":"beiN Sports HD* (US/CA | Main)"},{"id":"marveldcstream_28_333","title":"beiN Sports Espanyol HD* (US/CA | Main)"},{"id":"marveldcstream_28_334","title":"beiN Sports Connect 7 HD* (US/CA | Main)"},{"id":"marveldcstream_28_335","title":"beiN Sports Connect 6 HD* (US/CA | Main)"},{"id":"marveldcstream_28_336","title":"beiN Sports Connect 5 HD* (US/CA | Main)"},{"id":"marveldcstream_28_337","title":"beiN Sports Connect 4 HD* (US/CA | Main)"},{"id":"marveldcstream_28_338","title":"ACC Network Extra HD* (US/CA | Main) "},{"id":"marveldcstream_28_339","title":"ACC Network HD* (US/CA | Main)"},{"id":"marveldcstream_28_340","title":"=== USA Sports ==="},{"id":"marveldcstream_28_341","title":"HDNet Movies HD* (US/CA | Main) "},{"id":"marveldcstream_28_342","title":"IndiePlex HD* (US/CA | Main)"},{"id":"marveldcstream_28_343","title":"RetroPlex HD* (US/CA | Main) "},{"id":"marveldcstream_28_344","title":"MoviePlex HD* (US/CA | Main) "},{"id":"marveldcstream_28_345","title":"TCM HD* (US/CA | Main)"},{"id":"marveldcstream_28_346","title":"Starz West HD* (US/CA | Main)"},{"id":"marveldcstream_28_347","title":"Starz Kids & Family HD* (US/CA | Main)"},{"id":"marveldcstream_28_348","title":"Starz HD* (US/CA | Main)"},{"id":"marveldcstream_28_349","title":"Starz Encore Suspense HD* (US/CA | Main) "},{"id":"marveldcstream_28_350","title":"Starz Encore Classic HD* (US/CA | Main) "},{"id":"marveldcstream_28_351","title":"Starz Encore Black HD* (US/CA | Main) "},{"id":"marveldcstream_28_352","title":"Starz Encore Action HD* (US/CA | Main) "},{"id":"marveldcstream_28_353","title":"Starz Encore Western HD* (US/CA | Main)"},{"id":"marveldcstream_28_354","title":"Starz Encore West HD* (US/CA | Main)"},{"id":"marveldcstream_28_355","title":"Starz Encore HD* (US/CA | Main)"},{"id":"marveldcstream_28_356","title":"Starz Encore Family HD* (US/CA | Main)"},{"id":"marveldcstream_28_357","title":"Starz Edge HD* (US/CA | Main)"},{"id":"marveldcstream_28_358","title":"Starz Comedy HD* (US/CA | Main)"},{"id":"marveldcstream_28_359","title":"Starz Cinema HD* (US/CA | Main)"},{"id":"marveldcstream_28_360","title":"Starz Black HD* (US/CA | Main)"},{"id":"marveldcstream_28_361","title":"Sony Movie Channel HD* (US/CA | Main)"},{"id":"marveldcstream_28_362","title":"Showtime Women HD* (US/CA | Main)"},{"id":"marveldcstream_28_363","title":"Showtime Family Zone HD* (US/CA | Main)"},{"id":"marveldcstream_28_364","title":"Showtime Showcase HD* (US/CA | Main)"},{"id":"marveldcstream_28_365","title":"Showtime Next HD* (US/CA | Main)"},{"id":"marveldcstream_28_366","title":"Showtime HD* (US/CA | Main)"},{"id":"marveldcstream_28_367","title":"Showtime Extreme HD* (US/CA | Main)"},{"id":"marveldcstream_28_368","title":"Showtime Beyond HD* (US/CA | Main)"},{"id":"marveldcstream_28_369","title":"Showtime 2 HD* (US/CA | Main)"},{"id":"marveldcstream_28_370","title":"Showtime 2 (West) HD* (US/CA | Main)"},{"id":"marveldcstream_28_371","title":"NBC Cozi HD* (US/CA | Main)"},{"id":"marveldcstream_28_372","title":"Lifetime Movie Network HD* (US/CA | Main)"},{"id":"marveldcstream_28_373","title":"INSP HD* (US/CA | Main)"},{"id":"marveldcstream_28_374","title":"HBO Zone HD* (US/CA | Main)"},{"id":"marveldcstream_28_375","title":"HBO Signature HD* (US/CA | Main)"},{"id":"marveldcstream_28_376","title":"HBO HD* (US/CA | Main)"},{"id":"marveldcstream_28_377","title":"HBO Family HD* (US/CA | Main)"},{"id":"marveldcstream_28_378","title":"HBO Comedy HD* (US/CA | Main)"},{"id":"marveldcstream_28_379","title":"HBO 2 HD* (US/CA | Main)"},{"id":"marveldcstream_28_380","title":"Hallmark Movies & Mysteries HD* (US/CA | Main)"},{"id":"marveldcstream_28_381","title":"Hallmark Drama HD* (US/CA | Main)"},{"id":"marveldcstream_28_382","title":"Hallmark Channel HD* (US/CA | Main)"},{"id":"marveldcstream_28_383","title":"FXM HD* (US/CA | Main)"},{"id":"marveldcstream_28_384","title":"Epix Hits HD* (US/CA | Main)"},{"id":"marveldcstream_28_385","title":"Epix Drive In HD* (US/CA | Main)"},{"id":"marveldcstream_28_386","title":"Epix 2 HD* (US/CA | Main)"},{"id":"marveldcstream_28_387","title":"Epix HD* (US/CA | Main)"},{"id":"marveldcstream_28_388","title":"Cozi TV HD* (US/CA | Main)"},{"id":"marveldcstream_28_389","title":"Cinemax West HD* (US/CA | Main)"},{"id":"marveldcstream_28_390","title":"Cinemax Thrillermax HD* (US/CA | Main)"},{"id":"marveldcstream_28_391","title":"Cinemax Moremax HD* (US/CA | Main)"},{"id":"marveldcstream_28_392","title":"Cinemax East HD* (US/CA | Main)"},{"id":"marveldcstream_28_393","title":"Cinemax Actionmax HD* (US/CA | Main)"},{"id":"marveldcstream_28_394","title":"Cinemax 5Starmax HD* (US/CA | Main)"},{"id":"marveldcstream_28_395","title":"Cine Sony HD* (US/CA | Main)"},{"id":"marveldcstream_28_396","title":"=== USA Movies ==="},{"id":"marveldcstream_28_397","title":"Travel Channel Pacific HD* (US/CA | Main)"},{"id":"marveldcstream_28_398","title":"Travel Channel HD* (US/CA | Main)"},{"id":"marveldcstream_28_399","title":"National Geographic HD* (US/CA | Main)"},{"id":"marveldcstream_28_400","title":"Nat Geo Wild HD* (US/CA | Main)"},{"id":"marveldcstream_28_401","title":"Nat Geo Mundo HD* (US/CA | Main)"},{"id":"marveldcstream_28_402","title":"Motor Trend HD* (US/CA | Main)"},{"id":"marveldcstream_28_403","title":"Investigation Discovery HD* (US/CA | Main)"},{"id":"marveldcstream_28_404","title":"Info Wars HD* (US/CA | Main)"},{"id":"marveldcstream_28_405","title":"History HD* (US/CA | Main)"},{"id":"marveldcstream_28_406","title":"Food Network HD* (US/CA | Main)"},{"id":"marveldcstream_28_407","title":"Diy HD* (US/CA | Main)"},{"id":"marveldcstream_28_408","title":"Discovery Science HD* (US/CA | Main)"},{"id":"marveldcstream_28_409","title":"Discovery Life HD* (US/CA | Main)"},{"id":"marveldcstream_28_410","title":"Discovery HD* (US/CA | Main)"},{"id":"marveldcstream_28_411","title":"Discovery Family HD* (US/CA | Main)"},{"id":"marveldcstream_28_412","title":"Discovery Español HD* (US/CA | Main)"},{"id":"marveldcstream_28_413","title":"Destination America HD* (US/CA | Main)"},{"id":"marveldcstream_28_414","title":"Crime And Investigation HD* (US/CA | Main)"},{"id":"marveldcstream_28_415","title":"Animal Planet HD* (US/CA | Main)"},{"id":"marveldcstream_28_416","title":"=== USA Documentaries ==="},{"id":"marveldcstream_28_417","title":"WGN America HD* (US/CA | Main)"},{"id":"marveldcstream_28_418","title":"WGN (Chicago) HD* (US/CA | Main)"},{"id":"marveldcstream_28_419","title":"Weather Channel HD* (US/CA | Main)"},{"id":"marveldcstream_28_420","title":"WE TV HD* (US/CA | Main)"},{"id":"marveldcstream_28_421","title":"Viceland HD* (US/CA | Main)"},{"id":"marveldcstream_28_422","title":"VH1 HD* (US/CA | Main)"},{"id":"marveldcstream_28_423","title":"VH1 (West) HD* (US/CA | Main)"},{"id":"marveldcstream_28_424","title":"USA Network Pacific HD* (US/CA | Main)"},{"id":"marveldcstream_28_425","title":"USA Network HD* (US/CA | Main)"},{"id":"marveldcstream_28_426","title":"Univision L.A HD* (US/CA | Main)"},{"id":"marveldcstream_28_427","title":"Univision HD* (US/CA | Main)"},{"id":"marveldcstream_28_428","title":"Univision Deportes Network HD* (US/CA | Main)"},{"id":"marveldcstream_28_429","title":"Universo HD* (US/CA | Main)"},{"id":"marveldcstream_28_430","title":"Unimas HD* (US/CA | Main)"},{"id":"marveldcstream_28_431","title":"TV One HD* (US/CA | Main)"},{"id":"marveldcstream_28_432","title":"TV Land HD* (US/CA | Main)"},{"id":"marveldcstream_28_433","title":"TruTV Pacific HD* (US/CA | Main)"},{"id":"marveldcstream_28_434","title":"TruTv HD* (US/CA | Main)"},{"id":"marveldcstream_28_435","title":"TLC HD* (US/CA | Main)"},{"id":"marveldcstream_28_436","title":"Telemundo West HD* (US/CA | Main)"},{"id":"marveldcstream_28_437","title":"Telemundo Washington HD* (US/CA | Main)"},{"id":"marveldcstream_28_438","title":"Telemundo San Fransisco HD* (US/CA | Main)"},{"id":"marveldcstream_28_439","title":"Telemundo Phoenix HD* (US/CA | Main)"},{"id":"marveldcstream_28_440","title":"Telemundo Philadelphia HD* (US/CA | Main)"},{"id":"marveldcstream_28_441","title":"Telemundo New York HD* (US/CA | Main)"},{"id":"marveldcstream_28_442","title":"Telemundo Los Angeles HD* (US/CA | Main)"},{"id":"marveldcstream_28_443","title":"Telemundo Las Vegas HD* (US/CA | Main)"},{"id":"marveldcstream_28_444","title":"Telemundo International HD* (US/CA | Main)"},{"id":"marveldcstream_28_445","title":"Telemundo Houston HD* (US/CA | Main)"},{"id":"marveldcstream_28_446","title":"Telemundo HD* (US/CA | Main)"},{"id":"marveldcstream_28_447","title":"Telemundo Fresno HD* (US/CA | Main)"},{"id":"marveldcstream_28_448","title":"Telemundo Dallas HD* (US/CA | Main)"},{"id":"marveldcstream_28_449","title":"Telemundo Chicago HD* (US/CA | Main)"},{"id":"marveldcstream_28_450","title":"Telemundo Boston HD* (US/CA | Main)"},{"id":"marveldcstream_28_451","title":"Telemundo Atlanta HD* (US/CA | Main)"},{"id":"marveldcstream_28_452","title":"TBS HD* (US/CA | Main)"},{"id":"marveldcstream_28_453","title":"Syfy Pacific HD* (US/CA | Main)"},{"id":"marveldcstream_28_454","title":"Syfy HD* (US/CA | Main)"},{"id":"marveldcstream_28_455","title":"Sundance HD* (US/CA | Main)"},{"id":"marveldcstream_28_456","title":"Smithsonian HD* (US/CA | Main)"},{"id":"marveldcstream_28_457","title":"Revolt HD* (US/CA | Main)"},{"id":"marveldcstream_28_458","title":"Reelz HD* (US/CA | Main)"},{"id":"marveldcstream_28_459","title":"PBS HD* (US/CA | Main)"},{"id":"marveldcstream_28_460","title":"Paramount HD* (US/CA | Main)"},{"id":"marveldcstream_28_461","title":"Oxygen Pacific HD* (US/CA | Main)"},{"id":"marveldcstream_28_462","title":"Oxygen HD* (US/CA | Main)"},{"id":"marveldcstream_28_463","title":"Oprah Winfrey Network HD* (US/CA | Main)"},{"id":"marveldcstream_28_464","title":"NBC 5 Chicago HD* (US/CA | Main)"},{"id":"marveldcstream_28_465","title":"NBC 4 Washington HD* (US/CA | Main)"},{"id":"marveldcstream_28_466","title":"MY50 HD* (US/CA | Main)"},{"id":"marveldcstream_28_467","title":"MTVU HD* (US/CA | Main)"},{"id":"marveldcstream_28_468","title":"MTV2 HD* (US/CA | Main)"},{"id":"marveldcstream_28_469","title":"MTV Live HD* (US/CA | Main)"},{"id":"marveldcstream_28_470","title":"MTV HD* (US/CA | Main)"},{"id":"marveldcstream_28_471","title":"MTV Classic HD* (US/CA | Main)"},{"id":"marveldcstream_28_472","title":"Miami TV HD* (US/CA | Main)"},{"id":"marveldcstream_28_473","title":"ME TV HD* (US/CA | Main)"},{"id":"marveldcstream_28_474","title":"Logo HD* (US/CA | Main)"},{"id":"marveldcstream_28_475","title":"Lifetime HD* (US/CA | Main)"},{"id":"marveldcstream_28_476","title":"Ion Tv HD* (US/CA | Main)"},{"id":"marveldcstream_28_477","title":"IFC HD* (US/CA | Main)"},{"id":"marveldcstream_28_478","title":"HSN HD* (US/CA | Main)"},{"id":"marveldcstream_28_479","title":"HLN HD* (US/CA | Main)"},{"id":"marveldcstream_28_480","title":"HGTV HD* (US/CA | Main)"},{"id":"marveldcstream_28_481","title":"Grit HD* (US/CA | Main)"},{"id":"marveldcstream_28_482","title":"GolTV (English) HD* (US/CA | Main)"},{"id":"marveldcstream_28_483","title":"Global Vancouver HD* (US/CA | Main)"},{"id":"marveldcstream_28_484","title":"Game Show Network HD* (US/CA | Main)"},{"id":"marveldcstream_28_485","title":"Galavison HD* (US/CA | Main)"},{"id":"marveldcstream_28_486","title":"FYI HD* (US/CA | Main)"},{"id":"marveldcstream_28_487","title":"FXX HD* (US/CA | Main)"},{"id":"marveldcstream_28_488","title":"FX HD* (US/CA | Main)"},{"id":"marveldcstream_28_489","title":"Fusion HD* (US/CA | Main)"},{"id":"marveldcstream_28_490","title":"Fuse HD* (US/CA | Main)"},{"id":"marveldcstream_28_491","title":"Freeform HD* (US/CA | Main)"},{"id":"marveldcstream_28_492","title":"Fox Life HD* (US/CA | Main)"},{"id":"marveldcstream_28_493","title":"Fox HD* (US/CA | Main)"},{"id":"marveldcstream_28_494","title":"Fox 5 NY HD* (US/CA | Main)"},{"id":"marveldcstream_28_495","title":"Entertainment HD* (US/CA | Main)"},{"id":"marveldcstream_28_496","title":"ElRey Network HD* (US/CA | Main)"},{"id":"marveldcstream_28_497","title":"CW HD* (US/CA | Main)"},{"id":"marveldcstream_28_498","title":"Cooking Channel HD* (US/CA | Main)"},{"id":"marveldcstream_28_499","title":"Comet HD* (US/CA | Main)"},{"id":"marveldcstream_28_500","title":"Comedy Central HD* (US/CA | Main)"},{"id":"marveldcstream_28_501","title":"CMT HD* (US/CA | Main)"},{"id":"marveldcstream_28_502","title":"City HD* (US/CA | Main)"},{"id":"marveldcstream_28_503","title":"WXYZ|ABC Detroit|Michigan (US/CA | Regional)"},{"id":"marveldcstream_28_504","title":"Cheddar Stream HD* (US/CA | Main)"},{"id":"marveldcstream_28_505","title":"WSB|ABC Atlanta|Georgia (US/CA | Regional)"},{"id":"marveldcstream_28_506","title":"WPLG|ABC Miami|Florida (US/CA | Regional)"},{"id":"marveldcstream_28_507","title":"WFTV|ABC Orlando|Florida (US/CA | Regional)"},{"id":"marveldcstream_28_508","title":"WFAA|ABC Dallas|Fort Worth|Texas (US/CA | Regional)"},{"id":"marveldcstream_28_509","title":"Buzzer TV HD* (US/CA | Main)"},{"id":"marveldcstream_28_510","title":"Bravo HD* (US/CA | Main)"},{"id":"marveldcstream_28_511","title":"Bounce TV HD* (US/CA | Main)"},{"id":"marveldcstream_28_512","title":"KNXV|ABC Phoenix|Arizona (US/CA | Regional)"},{"id":"marveldcstream_28_513","title":"BET Soul HD* (US/CA | Main)"},{"id":"marveldcstream_28_514","title":"KMGH|ABC Denver|Colorado (US/CA | Regional)"},{"id":"marveldcstream_28_515","title":"BET Jams HD* (US/CA | Main)"},{"id":"marveldcstream_28_516","title":"KABC|ABC Los Angeles|California (US/CA | Regional)"},{"id":"marveldcstream_28_517","title":"BET International HD* (US/CA | Main)"},{"id":"marveldcstream_28_518","title":"====== ABC Locals ======"},{"id":"marveldcstream_28_519","title":"WXTV|Univision Paterson|New Jersey/New York|New York (US/CA | Regional)"},{"id":"marveldcstream_28_520","title":"WUVP|Univision Vineland|New Jersey (US/CA | Regional)"},{"id":"marveldcstream_28_521","title":"BBC America HD* (US/CA | Main)"},{"id":"marveldcstream_28_522","title":"AXS HD* (US/CA | Main)"},{"id":"marveldcstream_28_523","title":"American Wealth Entertainment HD* (US/CA | Main)"},{"id":"marveldcstream_28_524","title":"WLTV|Univision Miami|Florida (US/CA | Regional)"},{"id":"marveldcstream_28_525","title":"American Heroes HD* (US/CA | Main)"},{"id":"marveldcstream_28_526","title":"WGBO|Univision Joliet|Illinois (US/CA | Regional)"},{"id":"marveldcstream_28_527","title":"AMC HD* (US/CA | Main)"},{"id":"marveldcstream_28_528","title":"KXLN|Univision Rosenberg|Texas (US/CA | Regional)"},{"id":"marveldcstream_28_529","title":"AFN Prime Atlantic HD* (US/CA | Main)"},{"id":"marveldcstream_28_530","title":"KUVN|Univision Garland|Texas (US/CA | Regional)"},{"id":"marveldcstream_28_531","title":"ABC Spark HD* (US/CA | Main)"},{"id":"marveldcstream_28_532","title":"KTVW|Univision Phoenix|Arizona (US/CA | Regional)"},{"id":"marveldcstream_28_533","title":"KMEX|Univision Los Angeles|California (US/CA | Regional)"},{"id":"marveldcstream_28_534","title":"KFTR|Univision Ontario|California (US/CA | Regional)"},{"id":"marveldcstream_28_535","title":"KFSF|Univision Vallejo|California (US/CA | Regional)"},{"id":"marveldcstream_28_536","title":"KFPH|Univision Flagstaff|Arizona (US/CA | Regional)"},{"id":"marveldcstream_28_537","title":"KDTV|Univision San Francisco|California (US/CA | Regional)"},{"id":"marveldcstream_28_538","title":"KAKW|Univision Killeen|Texas (US/CA | Regional)"},{"id":"marveldcstream_28_539","title":"====== Univision Locals ======"},{"id":"marveldcstream_28_540","title":"WXFT|Unimas Aurora|Illinois (US/CA | Regional)"},{"id":"marveldcstream_28_541","title":"WFUT|Unimas Newark|New Jersey (US/CA | Regional)"},{"id":"marveldcstream_28_542","title":"WFPA|Unimas Philadelphia|Pennsylvania (US/CA | Regional)"},{"id":"marveldcstream_28_543","title":"WAMI|Unimas Hollywood|Florida (US/CA | Regional)"},{"id":"marveldcstream_28_544","title":"KTFO|Unimas Austin|Texas (US/CA | Regional)"},{"id":"marveldcstream_28_545","title":"KSTR|Unimas Irving|Texas (US/CA | Regional)"},{"id":"marveldcstream_28_546","title":"====== Unimas Locals ======"},{"id":"marveldcstream_28_547","title":"WZDC|Telemundo Washington|D.C. (US/CA | Regional)"},{"id":"marveldcstream_28_548","title":"WTMO|Telemundo Orlando|Florida (US/CA | Regional)"},{"id":"marveldcstream_28_549","title":"WSNS|Telemundo Chicago|Illinois (US/CA | Regional)"},{"id":"marveldcstream_28_550","title":"WSCV|Telemundo Fort Lauderdale|Florida (US/CA | Regional)"},{"id":"marveldcstream_28_551","title":"WRMD|Telemundo Tampa|Florida (US/CA | Regional)"},{"id":"marveldcstream_28_552","title":"WRDM|Telemundo Hartford|Connecticut (US/CA | Regional)"},{"id":"marveldcstream_28_553","title":"WNJU|Telemundo Linden|New Jersey (US/CA | Regional)"},{"id":"marveldcstream_28_554","title":"WNEU|Telemundo Merrimack|New Hampshire (US/CA | Regional)"},{"id":"marveldcstream_28_555","title":"WKTB|Telemundo Atlanta (US/CA | Regional)"},{"id":"marveldcstream_28_556","title":"KXTX|Telemundo Dallas|Texas (US/CA | Regional)"},{"id":"marveldcstream_28_557","title":"KVEA|Telemundo Corona|California (US/CA | Regional)"},{"id":"marveldcstream_28_558","title":"KTUZ|Telemundo Shawnee|Oklahoma (US/CA | Regional)"},{"id":"marveldcstream_28_559","title":"KTMW|Telemundo Salt Lake City|Utah (US/CA | Regional)"},{"id":"marveldcstream_28_560","title":"KTAZ|Telemundo Phoenix|Arizona (US/CA | Regional)"},{"id":"marveldcstream_28_561","title":"KSTS|Telemundo San Jose|California (US/CA | Regional)"},{"id":"marveldcstream_28_562","title":"KQRE|Telemundo Bend|Oregon (US/CA | Regional)"},{"id":"marveldcstream_28_563","title":"KGLA|Telemundo Hammond|Louisiana (US/CA | Regional)"},{"id":"marveldcstream_28_564","title":"KDEN|Telemundo Longmont|Colorado (US/CA | Regional)"},{"id":"marveldcstream_28_565","title":"KCSO|Telemundo Sacramento|California (US/CA | Regional)"},{"id":"marveldcstream_28_566","title":"KBLR|Telemundo Paradise|Nevada (US/CA | Regional)"},{"id":"marveldcstream_28_567","title":"====== Telemundo Locals ======"},{"id":"marveldcstream_28_568","title":"WXIA|NBC Atlanta|Georgia (US/CA | Regional)"},{"id":"marveldcstream_28_569","title":"WTVJ|NBC Miami|Florida (US/CA | Regional)"},{"id":"marveldcstream_28_570","title":"WSFA|NBC Montgomery|Alabama (US/CA | Regional)"},{"id":"marveldcstream_28_571","title":"WRC|NBC Washington|D.C. (US/CA | Regional)"},{"id":"marveldcstream_28_572","title":"WPXI|NBC Pittsburgh|Pennsylvania (US/CA | Regional)"},{"id":"marveldcstream_28_573","title":"WOWT|NBC Omaha|Nebraska (US/CA | Regional)"},{"id":"marveldcstream_28_574","title":"WNBC|NBC New York (US/CA | Regional)"},{"id":"marveldcstream_28_575","title":"WMTV|NBC Madison|Wisconsin (US/CA | Regional)"},{"id":"marveldcstream_28_576","title":"WMFP|NBC Foxborough|Massachusetts (US/CA | Regional)"},{"id":"marveldcstream_28_577","title":"WMAQ|NBC Chicago|Illinois (US/CA | Regional)"},{"id":"marveldcstream_28_578","title":"WKYC|NBC Cleveland|Ohio (US/CA | Regional)"},{"id":"marveldcstream_28_579","title":"WJAR|NBC Providence|Rhode Island (US/CA | Regional)"},{"id":"marveldcstream_28_580","title":"WIS|NBC Columbia|South Carolina (US/CA | Regional)"},{"id":"marveldcstream_28_581","title":"WGRZ|NBC Buffalo|New York (US/CA | Regional)"},{"id":"marveldcstream_28_582","title":"WDSU|NBC New Orleans|Louisiana (US/CA | Regional)"},{"id":"marveldcstream_28_583","title":"WCNC|NBC Charlotte|North Carolina (US/CA | Regional)"},{"id":"marveldcstream_28_584","title":"WCMH|NBC Columbus|Ohio (US/CA | Regional)"},{"id":"marveldcstream_28_585","title":"WBRE|NBC Wilkes Barre|Pennsylvania (US/CA | Regional)"},{"id":"marveldcstream_28_586","title":"WBOY|NBC Clarksburg|West Virginia (US/CA | Regional)"},{"id":"marveldcstream_28_587","title":"WBAL|NBC Baltimore|Maryland (US/CA | Regional)"},{"id":"marveldcstream_28_588","title":"KXAS|NBC Fort Worth|Dallas (US/CA | Regional)"},{"id":"marveldcstream_28_589","title":"KXAN|NBC Austin|Texas (US/CA | Regional)"},{"id":"marveldcstream_28_590","title":"KUSA|NBC Denver|Colorado (US/CA | Regional)"},{"id":"marveldcstream_28_591","title":"KSNV|NBC Las Vegas|Nevada (US/CA | Regional)"},{"id":"marveldcstream_28_592","title":"KSL|NBC Salt Lake City|Utah (US/CA | Regional)"},{"id":"marveldcstream_28_593","title":"KPRC|NBC Houston|Texas (US/CA | Regional)"},{"id":"marveldcstream_28_594","title":"KPNX|NBC Mesa|Arizona (US/CA | Regional)"},{"id":"marveldcstream_28_595","title":"KNTV|NBC San Jose|California (US/CA | Regional)"},{"id":"marveldcstream_28_596","title":"KNBC|NBC Los Angeles (US/CA | Regional)"},{"id":"marveldcstream_28_597","title":"KING|NBC Seattle|Washington (US/CA | Regional)"},{"id":"marveldcstream_28_598","title":"KHNL|NBC Honolulu|Hawaii (US/CA | Regional)"},{"id":"marveldcstream_28_599","title":"KDLT|NBC Sioux Falls|South Dakota (US/CA | Regional)"},{"id":"marveldcstream_28_600","title":"KCRA|NBC Sacramento|California (US/CA | Regional)"},{"id":"marveldcstream_28_601","title":"KCHY|NBC Casper|Wyoming (US/CA | Regional)"},{"id":"marveldcstream_28_602","title":"====== NBC Locals ======"},{"id":"marveldcstream_28_603","title":"WVUE|Fox New Orleans|Louisiana (US/CA | Regional)"},{"id":"marveldcstream_28_604","title":"WTTG|Fox Washington|D.C. (US/CA | Regional)"},{"id":"marveldcstream_28_605","title":"WTIC|Fox Hartford|Connecticut (US/CA | Regional)"},{"id":"marveldcstream_28_606","title":"WSVN|Fox Miami|Florida (US/CA | Regional)"},{"id":"marveldcstream_28_607","title":"WPWR|Fox Gary|Indiana (US/CA | Regional)"},{"id":"marveldcstream_28_608","title":"WNYW|Fox New York (US/CA | Regional)"},{"id":"marveldcstream_28_609","title":"WNAC|Fox Providence|Rhode Island (US/CA | Regional)"},{"id":"marveldcstream_28_610","title":"WJZY|Fox Belmont|North Carolina (US/CA | Regional)"},{"id":"marveldcstream_28_611","title":"WJW|Fox Cleveland|Ohio (US/CA | Regional)"},{"id":"marveldcstream_28_612","title":"WITI|Fox Milwaukee|Wisconsin (US/CA | Regional)"},{"id":"marveldcstream_28_613","title":"WHNS|Fox Greenville|South Carolina (US/CA | Regional)"},{"id":"marveldcstream_28_614","title":"WFXT|Fox Boston|Massachusetts (US/CA | Regional)"},{"id":"marveldcstream_28_615","title":"WFLD|Fox Chicago|Illinois (US/CA | Regional)"},{"id":"marveldcstream_28_616","title":"WAGA|Fox Atlanta|Georgia (US/CA | Regional)"},{"id":"marveldcstream_28_617","title":"KVVU|Fox Henderson|Nevada (US/CA | Regional)"},{"id":"marveldcstream_28_618","title":"KTXL|Fox Sacramento|California (US/CA | Regional)"},{"id":"marveldcstream_28_619","title":"KTVU|Fox Oakland|California (US/CA | Regional)"},{"id":"marveldcstream_28_620","title":"KTVI|Fox St. Louis|Missouri (US/CA | Regional)"},{"id":"marveldcstream_28_621","title":"KTTW|Fox Sioux Falls|South Dakota (US/CA | Regional)"},{"id":"marveldcstream_28_622","title":"KTTV|Fox Los Angeles|California (US/CA | Regional)"},{"id":"marveldcstream_28_623","title":"KTBC|Fox Austin|Texas (US/CA | Regional)"},{"id":"marveldcstream_28_624","title":"KSTU|Fox Salt Lake City|Utah (US/CA | Regional)"},{"id":"marveldcstream_28_625","title":"KSAZ|Fox Phoenix|Arizona (US/CA | Regional)"},{"id":"marveldcstream_28_626","title":"KRIV|Fox Houston|Texas (US/CA | Regional)"},{"id":"marveldcstream_28_627","title":"KICU|Fox San Jose|California (US/CA | Regional)"},{"id":"marveldcstream_28_628","title":"KHON|Fox Honolulu|Hawaii (US/CA | Regional)"},{"id":"marveldcstream_28_629","title":"KDVR|Fox Denver|Colorado (US/CA | Regional)"},{"id":"marveldcstream_28_630","title":"KDFW|Fox Dallas|Texas (US/CA | Regional)"},{"id":"marveldcstream_28_631","title":"KCPQ|Fox Tacoma|Washington (US/CA | Regional)"},{"id":"marveldcstream_28_632","title":"====== FOX Locals ======"},{"id":"marveldcstream_28_633","title":"WYOU|CBS Scranton|Pennsylvania (US/CA | Regional)"},{"id":"marveldcstream_28_634","title":"WWL|CBS New Orleans|Louisiana (US/CA | Regional)"},{"id":"marveldcstream_28_635","title":"WUSA|CBS Washington|D.C. (US/CA | Regional)"},{"id":"marveldcstream_28_636","title":"WUPA|CBS Atlanta|Georgia (US/CA | Regional)"},{"id":"marveldcstream_28_637","title":"WSPA|CBS Spartanburg|South Carolina (US/CA | Regional)"},{"id":"marveldcstream_28_638","title":"WPRI|CBS Providence|Rhode Island (US/CA | Regional)"},{"id":"marveldcstream_28_639","title":"WOIO|CBS Shaker Heights/Cleveland|Ohio (US/CA | Regional)"},{"id":"marveldcstream_28_640","title":"WLTX|CBS Columbia|South Carolina (US/CA | Regional)"},{"id":"marveldcstream_28_641","title":"WLNY|CBS Riverhead|New York (US/CA | Regional)"},{"id":"marveldcstream_28_642","title":"WJZ|CBS|Baltimore (US/CA | Regional)"},{"id":"marveldcstream_28_643","title":"WIVB|CBS Buffalo|New York (US/CA | Regional)"},{"id":"marveldcstream_28_644","title":"WISC|CBS Madison|Wisconsin (US/CA | Regional)"},{"id":"marveldcstream_28_645","title":"WGCL|CBS Atlanta|Georgia (US/CA | Regional)"},{"id":"marveldcstream_28_646","title":"WFOR|CBS Miami|Fort Lauderdale (US/CA | Regional)"},{"id":"marveldcstream_28_647","title":"WCBS|CBS New York (US/CA | Regional)"},{"id":"marveldcstream_28_648","title":"WBZ|CBS Boston (US/CA | Regional)"},{"id":"marveldcstream_28_649","title":"WBTV|CBS Charlotte|North Carolina (US/CA | Regional)"},{"id":"marveldcstream_28_650","title":"WBNS|CBS Columbus|Ohio (US/CA | Regional)"},{"id":"marveldcstream_28_651","title":"WBFS|CBS Miami|Florida (US/CA | Regional)"},{"id":"marveldcstream_28_652","title":"WBBM|CBS Chicago (US/CA | Regional)"},{"id":"marveldcstream_28_653","title":"WAKA|CBS Selma|Alabama (US/CA | Regional)"},{"id":"marveldcstream_28_654","title":"KWTV|CBS Oklahoma City|Oklahoma (US/CA | Regional)"},{"id":"marveldcstream_28_655","title":"KUTV|CBS Salt Lake City|Utah (US/CA | Regional)"},{"id":"marveldcstream_28_656","title":"KTXA|CBS Fort Worth|Texas (US/CA | Regional)"},{"id":"marveldcstream_28_657","title":"KTVT|CBS Fort Worth|Dallas (US/CA | Regional)"},{"id":"marveldcstream_28_658","title":"KSTW|CBS Tacoma–Seattle|Washington (US/CA | Regional)"},{"id":"marveldcstream_28_659","title":"KPIX|CBS San Francisco|Oakland|San Jose (US/CA | Regional)"},{"id":"marveldcstream_28_660","title":"KPHO|CBS Phoenix|Arizona (US/CA | Regional)"},{"id":"marveldcstream_28_661","title":"KMTV|CBS Omaha|Nebraska (US/CA | Regional)"},{"id":"marveldcstream_28_662","title":"KMOV|CBS St. Louis|Missouri (US/CA | Regional)"},{"id":"marveldcstream_28_663","title":"KLAS|CBS Las Vegas|Nevada (US/CA | Regional)"},{"id":"marveldcstream_28_664","title":"KIRO|CBS Seattle|Washington (US/CA | Regional)"},{"id":"marveldcstream_28_665","title":"KHOU|CBS Houston|Texas (US/CA | Regional)"},{"id":"marveldcstream_28_666","title":"KGMB|CBS Honolulu|Hawaii (US/CA | Regional)"},{"id":"marveldcstream_28_667","title":"KELO |CBS Sioux Falls|South Dakota (US/CA | Regional)"},{"id":"marveldcstream_28_668","title":"KDKA|CBS Pittsburgh (US/CA | Regional)"},{"id":"marveldcstream_28_669","title":"KCNC|CBS Denver (US/CA | Regional)"},{"id":"marveldcstream_28_670","title":"KCCI|CBS Des Moines|Iowa (US/CA | Regional)"},{"id":"marveldcstream_28_671","title":"KCBS|CBS Los Angeles (US/CA | Regional)"},{"id":"marveldcstream_28_672","title":"KCAL|CBS Los Angeles|California (US/CA | Regional)"},{"id":"marveldcstream_28_673","title":"KBCW|CBS San Francisco|California (US/CA | Regional)"},{"id":"marveldcstream_28_674","title":"====== CBS Locals ======"},{"id":"marveldcstream_28_675","title":"ESPN3 HD* (US/CA | Main)"},{"id":"marveldcstream_28_676","title":"NewsMax TV HD* (US/CA | Main)"},{"id":"marveldcstream_28_677","title":"Newsmax Channel HD* (US/CA | Main)"},{"id":"marveldcstream_28_678","title":"NE Cable News HD* (US/CA | Main)"},{"id":"marveldcstream_28_679","title":"MSNBC HD* (US/CA | Main)"},{"id":"marveldcstream_28_680","title":"Fox News HD* (US/CA | Main)"},{"id":"marveldcstream_28_681","title":"Fox Business HD* (US/CA | Main)"},{"id":"marveldcstream_28_682","title":"CP24 HD* (US/CA | Main)"},{"id":"marveldcstream_28_683","title":"CNN HD* (US/CA | Main)"},{"id":"marveldcstream_28_684","title":"CNBC World HD* (US/CA | Main)"},{"id":"marveldcstream_28_685","title":"CNBC HD* (US/CA | Main)"},{"id":"marveldcstream_28_686","title":"Cheddar News HD* (US/CA | Main)"},{"id":"marveldcstream_28_687","title":"Cheddar Business HD* (US/CA | Main)"},{"id":"marveldcstream_28_688","title":"CBS News HD* (US/CA | Main)"},{"id":"marveldcstream_28_689","title":"Bloomberg HD* (US/CA | Main)"},{"id":"marveldcstream_28_690","title":"BBC World News HD* (US/CA | Main)"},{"id":"marveldcstream_28_691","title":"ABC News HD* (US/CA | Main)"},{"id":"marveldcstream_28_692","title":"=== USA News ==="},{"id":"marveldcstream_28_693","title":"MC | Wonderama (US/CA | Main)"},{"id":"marveldcstream_28_694","title":"MC | Youth Hits (US/CA | Main)"},{"id":"marveldcstream_28_695","title":"MC | Adult Alternative (US/CA | Main)"},{"id":"marveldcstream_28_696","title":"MC | Ladies of R&B (US/CA | Main) "},{"id":"marveldcstream_28_697","title":"MC | R&B 2K (US/CA | Main)"},{"id":"marveldcstream_28_698","title":"MC | Soft Rock (US/CA | Main)"},{"id":"marveldcstream_28_699","title":"MC | 80's Music Video "},{"id":"marveldcstream_28_700","title":"MC | Radio Disney (US/CA | Main)"},{"id":"marveldcstream_28_701","title":"MC | Music Choice Play (US/CA | Main)"},{"id":"marveldcstream_28_702","title":"MC | Learn & Play (US/CA | Main)"},{"id":"marveldcstream_28_703","title":"MC | Y2K (US/CA | Main)"},{"id":"marveldcstream_28_704","title":"MC | Country Hits (US/CA | Main)"},{"id":"marveldcstream_28_705","title":"MC | Pop Latino (US/CA | Main)"},{"id":"marveldcstream_28_706","title":"MC | Musica Urbana (US/CA | Main)"},{"id":"marveldcstream_28_707","title":"MC | Music Choice Max (US/CA | Main)"},{"id":"marveldcstream_28_708","title":"MC | Mexicana (US/CA | Main)"},{"id":"marveldcstream_28_709","title":"MC | Kidz Only! (US/CA | Main)"},{"id":"marveldcstream_28_710","title":"MC | Kidz Bop (US/CA | Main)"},{"id":"marveldcstream_28_711","title":"MC | Brits + Hits (US/CA | Main)"},{"id":"marveldcstream_28_712","title":"MC | Alternative (US/CA | Main)"},{"id":"marveldcstream_28_713","title":"MC | Tropicales Music Videos (US/CA | Main)"},{"id":"marveldcstream_28_714","title":"MC | Toddler Tunes Music Videos (US/CA | Main)"},{"id":"marveldcstream_28_715","title":"MC | Todays Country Music Videos (US/CA | Main)"},{"id":"marveldcstream_28_716","title":"MC | Throwback Jamz Music Videos (US/CA | Main)"},{"id":"marveldcstream_28_717","title":"MC | Teen Beats Music Videos (US/CA | Main)"},{"id":"marveldcstream_28_718","title":"MC | Rock Music Videos (US/CA | Main)"},{"id":"marveldcstream_28_719","title":"MC | Rap Music Videos (US/CA | Main)"},{"id":"marveldcstream_28_720","title":"MC | Rap 2K Music Videos (US/CA | Main)"},{"id":"marveldcstream_28_721","title":"MC | R & B Soul Music Videos (US/CA | Main)"},{"id":"marveldcstream_28_722","title":"MC | Pop Hits Music Videos (US/CA | Main)"},{"id":"marveldcstream_28_723","title":"MC | Pop & Country Music Videos (US/CA | Main)"},{"id":"marveldcstream_28_724","title":"MC | Metal Music Videos (US/CA | Main)"},{"id":"marveldcstream_28_725","title":"MC | Indie Music Videos (US/CA | Main)"},{"id":"marveldcstream_28_726","title":"MC | Hit List Music Videos (US/CA | Main)"},{"id":"marveldcstream_28_727","title":"MC | Hip Hop and R & B Music Videos (US/CA | Main)"},{"id":"marveldcstream_28_728","title":"MC | Dance EDM Music Videos (US/CA | Main)"},{"id":"marveldcstream_28_729","title":"MC | 90s Music Video (US/CA | Main)"},{"id":"marveldcstream_28_730","title":"=== USA Music ==="},{"id":"marveldcstream_28_731","title":"YTV HD* (US/CA | Main)"},{"id":"marveldcstream_28_732","title":"Universal Kids HD* (US/CA | Main)"},{"id":"marveldcstream_28_733","title":"Treehouse HD* (US/CA | Main)"},{"id":"marveldcstream_28_734","title":"Teen Nick HD* (US/CA | Main)"},{"id":"marveldcstream_28_735","title":"Pop TV HD* (US/CA | Main)"},{"id":"marveldcstream_28_736","title":"Nicktoons HD* (US/CA | Main)"},{"id":"marveldcstream_28_737","title":"Nickelodeon HD* (US/CA | Main)"},{"id":"marveldcstream_28_738","title":"Nick Music HD* (US/CA | Main)"},{"id":"marveldcstream_28_739","title":"NIck Jr. HD* (US/CA | Main)"},{"id":"marveldcstream_28_740","title":"Disney XD HD* (US/CA | Main)"},{"id":"marveldcstream_28_741","title":"Disney Junior HD* (US/CA | Main)"},{"id":"marveldcstream_28_742","title":"Disney Channel HD* (US/CA | Main)"},{"id":"marveldcstream_28_743","title":"Cartoon Network HD* (US/CA | Main)"},{"id":"marveldcstream_28_744","title":"Boomerang HD* (US/CA | Main)"},{"id":"marveldcstream_28_745","title":"Baby TV HD* (US/CA | Main)"},{"id":"marveldcstream_28_746","title":"=== USA Kids ==="},{"id":"marveldcstream_28_747","title":"Zona Futbol HD* (US/CA | Main)"},{"id":"marveldcstream_28_748","title":"Yes Network HD* (US/CA | Main)"},{"id":"marveldcstream_28_749","title":"WWE Network HD* (US/CA | Main)"},{"id":"marveldcstream_28_750","title":"World Fishing Network HD* (US/CA | Main)"},{"id":"marveldcstream_28_751","title":"UFC 24/7 TV HD* (US/CA | Main)"},{"id":"marveldcstream_28_752","title":"TYC Sports HD* (US/CA | Main)"},{"id":"marveldcstream_28_753","title":"TVG Racing Network HD* (US/CA | Main)"},{"id":"marveldcstream_28_754","title":"TVG Racing Network Alt HD* (US/CA | Main)"},{"id":"marveldcstream_28_755","title":"TSN 5 HD* (US/CA | Main)"},{"id":"marveldcstream_28_756","title":"TSN 4 HD* (US/CA | Main)"},{"id":"marveldcstream_28_757","title":"TSN 3 HD* (US/CA | Main)"},{"id":"marveldcstream_28_758","title":"TSN 2 HD* (US/CA | Main)"},{"id":"marveldcstream_28_759","title":"TSN 1 HD* (US/CA | Main)"},{"id":"marveldcstream_28_760","title":"TNT HD* (US/CA | Main)"},{"id":"marveldcstream_28_761","title":"The Golf Channel HD* (US/CA | Main)"},{"id":"marveldcstream_28_762","title":"Tennis Channel HD* (US/CA | Main)"},{"id":"marveldcstream_28_763","title":"Stadium HD* (US/CA | Main)"},{"id":"marveldcstream_28_764","title":"Stadium 3 HD* (US/CA | Main)"},{"id":"marveldcstream_28_765","title":"Stadium 2 HD* (US/CA | Main)"},{"id":"marveldcstream_28_766","title":"Stadium 1 HD* (US/CA | Main)"},{"id":"marveldcstream_28_767","title":"Sportsman Channel HD* (US/CA | Main)"},{"id":"marveldcstream_28_768","title":"Sec Network HD* (US/CA | Main)"},{"id":"marveldcstream_28_769","title":"PAC 12 Washington HD* (US/CA | Main)"},{"id":"marveldcstream_28_770","title":"PAC 12 Oregon HD* (US/CA | Main)"},{"id":"marveldcstream_28_771","title":"PAC 12 Network HD* (US/CA | Main)"},{"id":"marveldcstream_28_772","title":"PAC 12 Mountain HD* (US/CA | Main)"},{"id":"marveldcstream_28_773","title":"PAC 12 LA HD* (US/CA | Main)"},{"id":"marveldcstream_28_774","title":"PAC 12 Bay Area HD* (US/CA | Main)"},{"id":"marveldcstream_28_775","title":"PAC 12 Arizona HD* (US/CA | Main)"},{"id":"marveldcstream_28_776","title":"Outside HD* (US/CA | Main)"},{"id":"marveldcstream_28_777","title":"Outdoor Channel HD* (US/CA | Main)"},{"id":"marveldcstream_28_778","title":"NHL Network HD* (US/CA | Main)"},{"id":"marveldcstream_28_779","title":"NFL Redzone HD* (US/CA | Main)"},{"id":"marveldcstream_28_780","title":"NFL Network HD* (US/CA | Main)"},{"id":"marveldcstream_28_781","title":"NESN HD* (US/CA | Main)"},{"id":"marveldcstream_28_782","title":"NBCSN HD* (US/CA | Main)"},{"id":"marveldcstream_28_783","title":"NBC Washington HD* (US/CA | Main)"},{"id":"marveldcstream_28_784","title":"NBC SNY HD* (US/CA | Main)"},{"id":"marveldcstream_28_785","title":"NBC Phili HD* (US/CA | Main)"},{"id":"marveldcstream_28_786","title":"NBC Olympic HD* (US/CA | Main)"},{"id":"marveldcstream_28_787","title":"NBC North West HD* (US/CA | Main)"},{"id":"marveldcstream_28_788","title":"NBC Chicago Plus HD* (US/CA | Main)"},{"id":"marveldcstream_28_789","title":"NBC Chicago HD* (US/CA | Main)"},{"id":"marveldcstream_28_790","title":"NBC California Plus HD* (US/CA | Main)"},{"id":"marveldcstream_28_791","title":"NBC California HD* (US/CA | Main)"},{"id":"marveldcstream_28_792","title":"NBC Boston HD* (US/CA | Main)"},{"id":"marveldcstream_28_793","title":"NBC Bay Area HD* (US/CA | Main)"},{"id":"marveldcstream_28_794","title":"NBA TV HD* (US/CA | Main)"},{"id":"marveldcstream_28_795","title":"MSG+ 222 HD* (US/CA | Main)"},{"id":"marveldcstream_28_796","title":"MSG+ 22 HD* (US/CA | Main)"},{"id":"marveldcstream_28_797","title":"MSG HD* (US/CA | Main)"},{"id":"marveldcstream_28_798","title":"MSG 2 HD* (US/CA | Main)"},{"id":"marveldcstream_28_799","title":"MLB StrikeZone HD* (US/CA | Main)"},{"id":"marveldcstream_28_800","title":"MLB Network HD* (US/CA | Main)"},{"id":"marveldcstream_28_801","title":"Mav TV HD* (US/CA | Main)"},{"id":"marveldcstream_28_802","title":"Longhorn Network HD* (US/CA | Main)"},{"id":"marveldcstream_28_803","title":"GolTV (Spanish) HD* (US/CA | Main)"},{"id":"marveldcstream_28_804","title":"Gnix Sports TV HD* (US/CA | Main)"},{"id":"marveldcstream_28_805","title":"GAME+ HD* (US/CA | Main)"},{"id":"marveldcstream_28_806","title":"Fubo Sports Network HD* (US/CA | Main)"},{"id":"marveldcstream_28_807","title":"Fox Sports Wisconsin HD* (US/CA | Main)"},{"id":"marveldcstream_28_808","title":"Fox Sports West HD* (US/CA | Main)"},{"id":"marveldcstream_28_809","title":"Fox Sports Tennessee HD* (US/CA | Main)"},{"id":"marveldcstream_28_810","title":"Fox Sports Sun HD* (US/CA | Main)"},{"id":"marveldcstream_28_811","title":"Fox Sports South West HD* (US/CA | Main)"},{"id":"marveldcstream_28_812","title":"Fox Sports South HD* (US/CA | Main)"},{"id":"marveldcstream_28_813","title":"Fox Sports South East HD* (US/CA | Main)"},{"id":"marveldcstream_28_814","title":"Fox Sports San Diego HD* (US/CA | Main)"},{"id":"marveldcstream_28_815","title":"Fox Sports Prime Ticket HD* (US/CA | Main)"},{"id":"marveldcstream_28_816","title":"Fox Sports Oklahoma HD* (US/CA | Main)"},{"id":"marveldcstream_28_817","title":"Fox Sports Ohio HD* (US/CA | Main)"},{"id":"marveldcstream_28_818","title":"Fox Sports North HD* (US/CA | Main)"},{"id":"marveldcstream_28_819","title":"Fox Sports New Orleans HD* (US/CA | Main)"},{"id":"marveldcstream_28_820","title":"Fox Sports Midwest HD* (US/CA | Main)"},{"id":"marveldcstream_28_821","title":"Fox Sports Indiana HD* (US/CA | Main)"},{"id":"marveldcstream_28_822","title":"Fox Sports Florida HD* (US/CA | Main)"},{"id":"marveldcstream_28_823","title":"Fox Sports Detroit HD* (US/CA | Main)"},{"id":"marveldcstream_28_824","title":"Fox Sports Deportes HD* (US/CA | Main)"},{"id":"marveldcstream_28_825","title":"Fox Sports Carolinas HD* (US/CA | Main)"},{"id":"marveldcstream_28_826","title":"Fox Sports Arizona HD* (US/CA | Main)"},{"id":"marveldcstream_28_827","title":"Fox Sports 2 HD* (US/CA | Main)"},{"id":"marveldcstream_28_828","title":"Fox Sports 1 HD* (US/CA | Main)"},{"id":"marveldcstream_28_829","title":"Fox Soccer Plus HD* (US/CA | Main)"},{"id":"marveldcstream_28_830","title":"Fox College Sports Atlantic HD* (US/CA | Main)"},{"id":"marveldcstream_28_831","title":"FNTSY Sports Network HD* (US/CA | Main)"},{"id":"marveldcstream_28_832","title":"Fight Network HD* (US/CA | Main)"},{"id":"marveldcstream_28_833","title":"ESPNU HD* (US/CA | Main)"},{"id":"marveldcstream_28_834","title":"ESPNews HD* (US/CA | Main)"},{"id":"marveldcstream_28_835","title":"ESPN2 HD* (US/CA | Main)"},{"id":"marveldcstream_28_836","title":"ESPN HD* (US/CA | Main)"},{"id":"marveldcstream_28_837","title":"ESPN Deportes HD* (US/CA | Main)"},{"id":"marveldcstream_28_838","title":"ESPN Bases Loaded HD* (US/CA | Main)"},{"id":"marveldcstream_28_839","title":"Eleven Sports Network HD* (US/CA | Main)"},{"id":"marveldcstream_28_840","title":"CBS Sports Network HD* (US/CA | Main)"},{"id":"marveldcstream_28_841","title":"CBS Sports HQ HD* (US/CA | Main)"},{"id":"marveldcstream_28_842","title":"BTN HD* (US/CA | Main)"},{"id":"marveldcstream_28_843","title":"BTN Alternate HD* (US/CA | Main)"},{"id":"marveldcstream_28_844","title":"beiN Sports La Liga HD* (US/CA | Main)"},{"id":"marveldcstream_28_845","title":"beiN Sports HD* (US/CA | Main)"},{"id":"marveldcstream_28_846","title":"beiN Sports Espanyol HD* (US/CA | Main)"},{"id":"marveldcstream_28_847","title":"beiN Sports Connect 7 HD* (US/CA | Main)"},{"id":"marveldcstream_28_848","title":"beiN Sports Connect 6 HD* (US/CA | Main)"},{"id":"marveldcstream_28_849","title":"beiN Sports Connect 5 HD* (US/CA | Main)"},{"id":"marveldcstream_28_850","title":"beiN Sports Connect 4 HD* (US/CA | Main)"},{"id":"marveldcstream_28_851","title":"ACC Network Extra HD* (US/CA | Main) "},{"id":"marveldcstream_28_852","title":"ACC Network HD* (US/CA | Main)"},{"id":"marveldcstream_28_853","title":"=== USA Sports ==="},{"id":"marveldcstream_28_854","title":"HDNet Movies HD* (US/CA | Main) "},{"id":"marveldcstream_28_855","title":"IndiePlex HD* (US/CA | Main)"},{"id":"marveldcstream_28_856","title":"RetroPlex HD* (US/CA | Main) "},{"id":"marveldcstream_28_857","title":"MoviePlex HD* (US/CA | Main) "},{"id":"marveldcstream_28_858","title":"TCM HD* (US/CA | Main)"},{"id":"marveldcstream_28_859","title":"Starz West HD* (US/CA | Main)"},{"id":"marveldcstream_28_860","title":"Starz Kids & Family HD* (US/CA | Main)"},{"id":"marveldcstream_28_861","title":"Starz HD* (US/CA | Main)"},{"id":"marveldcstream_28_862","title":"Starz Encore Suspense HD* (US/CA | Main) "},{"id":"marveldcstream_28_863","title":"Starz Encore Classic HD* (US/CA | Main) "},{"id":"marveldcstream_28_864","title":"Starz Encore Black HD* (US/CA | Main) "},{"id":"marveldcstream_28_865","title":"Starz Encore Action HD* (US/CA | Main) "},{"id":"marveldcstream_28_866","title":"Starz Encore Western HD* (US/CA | Main)"},{"id":"marveldcstream_28_867","title":"Starz Encore West HD* (US/CA | Main)"},{"id":"marveldcstream_28_868","title":"Starz Encore HD* (US/CA | Main)"},{"id":"marveldcstream_28_869","title":"Starz Encore Family HD* (US/CA | Main)"},{"id":"marveldcstream_28_870","title":"Starz Edge HD* (US/CA | Main)"},{"id":"marveldcstream_28_871","title":"Starz Comedy HD* (US/CA | Main)"},{"id":"marveldcstream_28_872","title":"Starz Cinema HD* (US/CA | Main)"},{"id":"marveldcstream_28_873","title":"Starz Black HD* (US/CA | Main)"},{"id":"marveldcstream_28_874","title":"Sony Movie Channel HD* (US/CA | Main)"},{"id":"marveldcstream_28_875","title":"Showtime Women HD* (US/CA | Main)"},{"id":"marveldcstream_28_876","title":"Showtime Family Zone HD* (US/CA | Main)"},{"id":"marveldcstream_28_877","title":"Showtime Showcase HD* (US/CA | Main)"},{"id":"marveldcstream_28_878","title":"Showtime Next HD* (US/CA | Main)"},{"id":"marveldcstream_28_879","title":"Showtime HD* (US/CA | Main)"},{"id":"marveldcstream_28_880","title":"Showtime Extreme HD* (US/CA | Main)"},{"id":"marveldcstream_28_881","title":"Showtime Beyond HD* (US/CA | Main)"},{"id":"marveldcstream_28_882","title":"Showtime 2 HD* (US/CA | Main)"},{"id":"marveldcstream_28_883","title":"Showtime 2 (West) HD* (US/CA | Main)"},{"id":"marveldcstream_28_884","title":"NBC Cozi HD* (US/CA | Main)"},{"id":"marveldcstream_28_885","title":"Lifetime Movie Network HD* (US/CA | Main)"},{"id":"marveldcstream_28_886","title":"INSP HD* (US/CA | Main)"},{"id":"marveldcstream_28_887","title":"HBO Zone HD* (US/CA | Main)"},{"id":"marveldcstream_28_888","title":"HBO Signature HD* (US/CA | Main)"},{"id":"marveldcstream_28_889","title":"HBO HD* (US/CA | Main)"},{"id":"marveldcstream_28_890","title":"HBO Family HD* (US/CA | Main)"},{"id":"marveldcstream_28_891","title":"HBO Comedy HD* (US/CA | Main)"},{"id":"marveldcstream_28_892","title":"HBO 2 HD* (US/CA | Main)"},{"id":"marveldcstream_28_893","title":"Hallmark Movies & Mysteries HD* (US/CA | Main)"},{"id":"marveldcstream_28_894","title":"Hallmark Drama HD* (US/CA | Main)"},{"id":"marveldcstream_28_895","title":"Hallmark Channel HD* (US/CA | Main)"},{"id":"marveldcstream_28_896","title":"FXM HD* (US/CA | Main)"},{"id":"marveldcstream_28_897","title":"Epix Hits HD* (US/CA | Main)"},{"id":"marveldcstream_28_898","title":"Epix Drive In HD* (US/CA | Main)"},{"id":"marveldcstream_28_899","title":"Epix 2 HD* (US/CA | Main)"},{"id":"marveldcstream_28_900","title":"Epix HD* (US/CA | Main)"},{"id":"marveldcstream_28_901","title":"Cozi TV HD* (US/CA | Main)"},{"id":"marveldcstream_28_902","title":"Cinemax West HD* (US/CA | Main)"},{"id":"marveldcstream_28_903","title":"Cinemax Thrillermax HD* (US/CA | Main)"},{"id":"marveldcstream_28_904","title":"Cinemax Moremax HD* (US/CA | Main)"},{"id":"marveldcstream_28_905","title":"Cinemax East HD* (US/CA | Main)"},{"id":"marveldcstream_28_906","title":"Cinemax Actionmax HD* (US/CA | Main)"},{"id":"marveldcstream_28_907","title":"Cinemax 5Starmax HD* (US/CA | Main)"},{"id":"marveldcstream_28_908","title":"Cine Sony HD* (US/CA | Main)"},{"id":"marveldcstream_28_909","title":"=== USA Movies ==="},{"id":"marveldcstream_28_910","title":"Travel Channel Pacific HD* (US/CA | Main)"},{"id":"marveldcstream_28_911","title":"Travel Channel HD* (US/CA | Main)"},{"id":"marveldcstream_28_912","title":"National Geographic HD* (US/CA | Main)"},{"id":"marveldcstream_28_913","title":"Nat Geo Wild HD* (US/CA | Main)"},{"id":"marveldcstream_28_914","title":"Nat Geo Mundo HD* (US/CA | Main)"},{"id":"marveldcstream_28_915","title":"Motor Trend HD* (US/CA | Main)"},{"id":"marveldcstream_28_916","title":"Investigation Discovery HD* (US/CA | Main)"},{"id":"marveldcstream_28_917","title":"Info Wars HD* (US/CA | Main)"},{"id":"marveldcstream_28_918","title":"History HD* (US/CA | Main)"},{"id":"marveldcstream_28_919","title":"Food Network HD* (US/CA | Main)"},{"id":"marveldcstream_28_920","title":"Diy HD* (US/CA | Main)"},{"id":"marveldcstream_28_921","title":"Discovery Science HD* (US/CA | Main)"},{"id":"marveldcstream_28_922","title":"Discovery Life HD* (US/CA | Main)"},{"id":"marveldcstream_28_923","title":"Discovery HD* (US/CA | Main)"},{"id":"marveldcstream_28_924","title":"Discovery Family HD* (US/CA | Main)"},{"id":"marveldcstream_28_925","title":"Discovery Español HD* (US/CA | Main)"},{"id":"marveldcstream_28_926","title":"Destination America HD* (US/CA | Main)"},{"id":"marveldcstream_28_927","title":"Crime And Investigation HD* (US/CA | Main)"},{"id":"marveldcstream_28_928","title":"Animal Planet HD* (US/CA | Main)"},{"id":"marveldcstream_28_929","title":"=== USA Documentaries ==="},{"id":"marveldcstream_28_930","title":"WGN America HD* (US/CA | Main)"},{"id":"marveldcstream_28_931","title":"WGN (Chicago) HD* (US/CA | Main)"},{"id":"marveldcstream_28_932","title":"Weather Channel HD* (US/CA | Main)"},{"id":"marveldcstream_28_933","title":"WE TV HD* (US/CA | Main)"},{"id":"marveldcstream_28_934","title":"Viceland HD* (US/CA | Main)"},{"id":"marveldcstream_28_935","title":"VH1 HD* (US/CA | Main)"},{"id":"marveldcstream_28_936","title":"VH1 (West) HD* (US/CA | Main)"},{"id":"marveldcstream_28_937","title":"USA Network Pacific HD* (US/CA | Main)"},{"id":"marveldcstream_28_938","title":"USA Network HD* (US/CA | Main)"},{"id":"marveldcstream_28_939","title":"Univision L.A HD* (US/CA | Main)"},{"id":"marveldcstream_28_940","title":"Univision HD* (US/CA | Main)"},{"id":"marveldcstream_28_941","title":"Univision Deportes Network HD* (US/CA | Main)"},{"id":"marveldcstream_28_942","title":"Universo HD* (US/CA | Main)"},{"id":"marveldcstream_28_943","title":"Unimas HD* (US/CA | Main)"},{"id":"marveldcstream_28_944","title":"TV One HD* (US/CA | Main)"},{"id":"marveldcstream_28_945","title":"TV Land HD* (US/CA | Main)"},{"id":"marveldcstream_28_946","title":"TruTV Pacific HD* (US/CA | Main)"},{"id":"marveldcstream_28_947","title":"TruTv HD* (US/CA | Main)"},{"id":"marveldcstream_28_948","title":"TLC HD* (US/CA | Main)"},{"id":"marveldcstream_28_949","title":"Telemundo West HD* (US/CA | Main)"},{"id":"marveldcstream_28_950","title":"Telemundo Washington HD* (US/CA | Main)"},{"id":"marveldcstream_28_951","title":"Telemundo San Fransisco HD* (US/CA | Main)"},{"id":"marveldcstream_28_952","title":"Telemundo Phoenix HD* (US/CA | Main)"},{"id":"marveldcstream_28_953","title":"Telemundo Philadelphia HD* (US/CA | Main)"},{"id":"marveldcstream_28_954","title":"Telemundo New York HD* (US/CA | Main)"},{"id":"marveldcstream_28_955","title":"Telemundo Los Angeles HD* (US/CA | Main)"},{"id":"marveldcstream_28_956","title":"Telemundo Las Vegas HD* (US/CA | Main)"},{"id":"marveldcstream_28_957","title":"Telemundo International HD* (US/CA | Main)"},{"id":"marveldcstream_28_958","title":"Telemundo Houston HD* (US/CA | Main)"},{"id":"marveldcstream_28_959","title":"Telemundo HD* (US/CA | Main)"},{"id":"marveldcstream_28_960","title":"Telemundo Fresno HD* (US/CA | Main)"},{"id":"marveldcstream_28_961","title":"Telemundo Dallas HD* (US/CA | Main)"},{"id":"marveldcstream_28_962","title":"Telemundo Chicago HD* (US/CA | Main)"},{"id":"marveldcstream_28_963","title":"Telemundo Boston HD* (US/CA | Main)"},{"id":"marveldcstream_28_964","title":"Telemundo Atlanta HD* (US/CA | Main)"},{"id":"marveldcstream_28_965","title":"TBS HD* (US/CA | Main)"},{"id":"marveldcstream_28_966","title":"Syfy Pacific HD* (US/CA | Main)"},{"id":"marveldcstream_28_967","title":"Syfy HD* (US/CA | Main)"},{"id":"marveldcstream_28_968","title":"Sundance HD* (US/CA | Main)"},{"id":"marveldcstream_28_969","title":"Smithsonian HD* (US/CA | Main)"},{"id":"marveldcstream_28_970","title":"Revolt HD* (US/CA | Main)"},{"id":"marveldcstream_28_971","title":"Reelz HD* (US/CA | Main)"},{"id":"marveldcstream_28_972","title":"PBS HD* (US/CA | Main)"},{"id":"marveldcstream_28_973","title":"Paramount HD* (US/CA | Main)"},{"id":"marveldcstream_28_974","title":"Oxygen Pacific HD* (US/CA | Main)"},{"id":"marveldcstream_28_975","title":"Oxygen HD* (US/CA | Main)"},{"id":"marveldcstream_28_976","title":"Oprah Winfrey Network HD* (US/CA | Main)"},{"id":"marveldcstream_28_977","title":"NBC 5 Chicago HD* (US/CA | Main)"},{"id":"marveldcstream_28_978","title":"NBC 4 Washington HD* (US/CA | Main)"},{"id":"marveldcstream_28_979","title":"MY50 HD* (US/CA | Main)"},{"id":"marveldcstream_28_980","title":"MTVU HD* (US/CA | Main)"},{"id":"marveldcstream_28_981","title":"MTV2 HD* (US/CA | Main)"},{"id":"marveldcstream_28_982","title":"MTV Live HD* (US/CA | Main)"},{"id":"marveldcstream_28_983","title":"MTV HD* (US/CA | Main)"},{"id":"marveldcstream_28_984","title":"MTV Classic HD* (US/CA | Main)"},{"id":"marveldcstream_28_985","title":"Miami TV HD* (US/CA | Main)"},{"id":"marveldcstream_28_986","title":"ME TV HD* (US/CA | Main)"},{"id":"marveldcstream_28_987","title":"Logo HD* (US/CA | Main)"},{"id":"marveldcstream_28_988","title":"Lifetime HD* (US/CA | Main)"},{"id":"marveldcstream_28_989","title":"Ion Tv HD* (US/CA | Main)"},{"id":"marveldcstream_28_990","title":"IFC HD* (US/CA | Main)"},{"id":"marveldcstream_28_991","title":"HSN HD* (US/CA | Main)"},{"id":"marveldcstream_28_992","title":"HLN HD* (US/CA | Main)"},{"id":"marveldcstream_28_993","title":"HGTV HD* (US/CA | Main)"},{"id":"marveldcstream_28_994","title":"Grit HD* (US/CA | Main)"},{"id":"marveldcstream_28_995","title":"GolTV (English) HD* (US/CA | Main)"},{"id":"marveldcstream_28_996","title":"Global Vancouver HD* (US/CA | Main)"},{"id":"marveldcstream_28_997","title":"Game Show Network HD* (US/CA | Main)"},{"id":"marveldcstream_28_998","title":"Galavison HD* (US/CA | Main)"},{"id":"marveldcstream_28_999","title":"FYI HD* (US/CA | Main)"},{"id":"marveldcstream_28_1000","title":"FXX HD* (US/CA | Main)"},{"id":"marveldcstream_28_1001","title":"FX HD* (US/CA | Main)"},{"id":"marveldcstream_28_1002","title":"Fusion HD* (US/CA | Main)"},{"id":"marveldcstream_28_1003","title":"Fuse HD* (US/CA | Main)"},{"id":"marveldcstream_28_1004","title":"Freeform HD* (US/CA | Main)"},{"id":"marveldcstream_28_1005","title":"Fox Life HD* (US/CA | Main)"},{"id":"marveldcstream_28_1006","title":"Fox HD* (US/CA | Main)"},{"id":"marveldcstream_28_1007","title":"Fox 5 NY HD* (US/CA | Main)"},{"id":"marveldcstream_28_1008","title":"Entertainment HD* (US/CA | Main)"},{"id":"marveldcstream_28_1009","title":"ElRey Network HD* (US/CA | Main)"},{"id":"marveldcstream_28_1010","title":"CW HD* (US/CA | Main)"},{"id":"marveldcstream_28_1011","title":"Cooking Channel HD* (US/CA | Main)"},{"id":"marveldcstream_28_1012","title":"Comet HD* (US/CA | Main)"},{"id":"marveldcstream_28_1013","title":"Comedy Central HD* (US/CA | Main)"},{"id":"marveldcstream_28_1014","title":"CMT HD* (US/CA | Main)"},{"id":"marveldcstream_28_1015","title":"City HD* (US/CA | Main)"},{"id":"marveldcstream_28_1016","title":"Cheddar Stream HD* (US/CA | Main)"},{"id":"marveldcstream_28_1017","title":"CHCH HD* (US/CA | Main)"},{"id":"marveldcstream_28_1018","title":"CBS Pop HD* (US/CA | Main)"},{"id":"marveldcstream_28_1019","title":"CBS HD* (US/CA | Main)"},{"id":"marveldcstream_28_1020","title":"CBC Toronto HD* (US/CA | Main)"},{"id":"marveldcstream_28_1021","title":"Buzzer TV HD* (US/CA | Main)"},{"id":"marveldcstream_28_1022","title":"Bravo HD* (US/CA | Main)"},{"id":"marveldcstream_28_1023","title":"Bounce TV HD* (US/CA | Main)"},{"id":"marveldcstream_28_1024","title":"BET Soul HD* (US/CA | Main)"},{"id":"marveldcstream_28_1025","title":"BET Jams HD* (US/CA | Main)"},{"id":"marveldcstream_28_1026","title":"BET International HD* (US/CA | Main)"},{"id":"marveldcstream_28_1027","title":"BET Her HD* (US/CA | Main)"},{"id":"marveldcstream_28_1028","title":"BET HD* (US/CA | Main)"},{"id":"marveldcstream_28_1029","title":"BET (West) HD* (US/CA | Main)"},{"id":"marveldcstream_28_1030","title":"BBC America HD* (US/CA | Main)"},{"id":"marveldcstream_28_1031","title":"AXS HD* (US/CA | Main)"},{"id":"marveldcstream_28_1032","title":"American Wealth Entertainment HD* (US/CA | Main)"},{"id":"marveldcstream_28_1033","title":"American Heroes HD* (US/CA | Main)"},{"id":"marveldcstream_28_1034","title":"AMC HD* (US/CA | Main)"},{"id":"marveldcstream_28_1035","title":"AFN Prime Atlantic HD* (US/CA | Main)"},{"id":"marveldcstream_28_1036","title":"ABC Spark HD* (US/CA | Main)"},{"id":"marveldcstream_28_1037","title":"ABC HD* (US/CA | Main)"},{"id":"marveldcstream_28_1038","title":"A&E HD* (US/CA | Main)"}]}}